Workbook

Sheet 說明
A1: 負面新聞離線覆核（30 筆小樣本）
A2: 產生日期：2026-10-26 範圍：L5 待人工覆核 15 筆＋L4 15 筆
A4: 怎麼填（只動黃色欄位）
A5: 1. 最終決定（Q 欄）：已預填我的建議。維持＝沿用目前分類；修改＝改成「新事件代碼」；排除＝記為 NOT_RELEVANT、Level 0。
A6: 2. 新事件代碼（R 欄）：只有「修改」才需要，從下拉選單選；新事件中文與新 Level 會自動帶出。
A7: 3. 覆核註記（V 欄）、覆核人（W 欄）：請填你的姓名；註記可空白。
A8: 4. 把握程度為「低」或「建議看原文」為「是」的列（紅字），建議點標題開原文確認。
A9: 5. 檢查欄（U）若出現紅字，表示該列填寫不完整。
A10: 6. 不要修改 news_id、人工版本欄；上傳時靠這兩欄對應與防衝突。
A12: 限制
A13: 我只看資料中的標題與摘要，沒有逐篇開原文；建議不保證全對，最終由你確認。
A14: Level 顏色：5 紅、4 橘、3 黃、2 淡藍、1 淺灰、0 深灰。

Sheet 覆核
A1: 序號 | B1: 日期 | C1: Ticker | D1: 公司 | E1: 標題（點擊開原文） | F1: 中文標題／摘要 | G1: 來源 | H1: FinBERT | I1: 目前事件代碼 | J1: 目前事件中文 | K1: 目前Level | L1: 建議 | M1: 建議事件代碼 | N1: 把握程度 | O1: 理由 | P1: 建議看原文 | Q1: 最終決定 | R1: 新事件代碼 | S1: 新事件中文 | T1: 新Level | U1: 檢查 | V1: 覆核註記 | W1: 覆核人 | X1: news_id | Y1: 人工版本
A2: 1 | B2: 2026-10-23 | C2: GETY | D2: Getty Images Holdings, Inc. | E2: Getty Images Files Prepackaged Chapter 11 in Delaware | F2: Getty Images 申請預先包裝的第11章破產程序，表明公司正進入破產程序。 | G2: ABF Journal | I2: BANKRUPTCY | J2: 破產 | K2: 5 | L2: 維持 | N2: 高 | O2: Getty Images 申請預先包裝式 Chapter 11（Delaware）。 | Q2: 維持 | S2: =IF(Q2="維持",J2,IF(Q2="排除","無關新聞事件",IFERROR(INDEX(事件規則!$B$2:$B$53,MATCH(R2,事件規則!$A$2:$A$53,0)),""))) -> 破產 | T2: =IF(Q2="維持",K2,IF(Q2="排除",0,IFERROR(INDEX(事件規則!$C$2:$C$53,MATCH(R2,事件規則!$A$2:$A$53,0)),""))) -> 5 | U2: =IF(AND(Q2="修改",R2=""),"請選新事件代碼",IF(AND(Q2<>"修改",R2<>""),"只有「修改」才需填代碼","")) | X2: 26a1ad393c1cc9e9c11186e2
A3: 2 | B3: 2026-10-23 | C3: GETY | D3: Getty Images Holdings, Inc. | E3: Getty Images’ Reported Chapter 11 Filing Would Cancel Shares | F3: Getty Images 已報告將進行第 11 章破產申請，將取消其股份。 | G3: FindArticles | I3: BANKRUPTCY | J3: 破產 | K3: 5 | L3: 維持 | N3: 高 | O3: Getty Images Chapter 11（與前一則同一事件，重複報導）。 | Q3: 維持 | S3: =IF(Q3="維持",J3,IF(Q3="排除","無關新聞事件",IFERROR(INDEX(事件規則!$B$2:$B$53,MATCH(R3,事件規則!$A$2:$A$53,0)),""))) -> 破產 | T3: =IF(Q3="維持",K3,IF(Q3="排除",0,IFERROR(INDEX(事件規則!$C$2:$C$53,MATCH(R3,事件規則!$A$2:$A$53,0)),""))) -> 5 | U3: =IF(AND(Q3="修改",R3=""),"請選新事件代碼",IF(AND(Q3<>"修改",R3<>""),"只有「修改」才需填代碼","")) | X3: 2dcb018737c84e3d434366ac
A4: 3 | B4: 2026-10-23 | C4: GETY | D4: Getty Images Holdings, Inc. | E4: Case Summary: Getty Images Chapter 11 | F4: Getty Images 已經提交第11章破產申請，正式進入破產程序。 | G4: Bondoro | I4: BANKRUPTCY | J4: 破產 | K4: 5 | L4: 維持 | N4: 高 | O4: Getty Images Chapter 11 案件摘要（同一事件，重複報導）。 | Q4: 維持 | S4: =IF(Q4="維持",J4,IF(Q4="排除","無關新聞事件",IFERROR(INDEX(事件規則!$B$2:$B$53,MATCH(R4,事件規則!$A$2:$A$53,0)),""))) -> 破產 | T4: =IF(Q4="維持",K4,IF(Q4="排除",0,IFERROR(INDEX(事件規則!$C$2:$C$53,MATCH(R4,事件規則!$A$2:$A$53,0)),""))) -> 5 | U4: =IF(AND(Q4="修改",R4=""),"請選新事件代碼",IF(AND(Q4<>"修改",R4<>""),"只有「修改」才需填代碼","")) | X4: f097dfc93880c10c18a4ffdc
A5: 4 | B5: 2026-10-22 | C5: EONR | D5: EON Resources Inc. Class A Common Stock | E5: Eon Resources CEO Defends Liquidity Despite Recurring Going-Concern Warnings | F5: Eon Resources 公司的 CEO 在面臨持續的營運疑慮警告時，表示公司仍具足夠流動性以維持營運。 | G5: Hart Energy | I5: GOING_CONCERN | J5: 繼續經營疑慮 | K5: 5 | L5: 維持 | N5: 高 | O5: 標題明指持續的繼續經營疑慮（going-concern）警告。 | Q5: 維持 | S5: =IF(Q5="維持",J5,IF(Q5="排除","無關新聞事件",IFERROR(INDEX(事件規則!$B$2:$B$53,MATCH(R5,事件規則!$A$2:$A$53,0)),""))) -> 繼續經營疑慮 | T5: =IF(Q5="維持",K5,IF(Q5="排除",0,IFERROR(INDEX(事件規則!$C$2:$C$53,MATCH(R5,事件規則!$A$2:$A$53,0)),""))) -> 5 | U5: =IF(AND(Q5="修改",R5=""),"請選新事件代碼",IF(AND(Q5<>"修改",R5<>""),"只有「修改」才需填代碼","")) | X5: a18bd00bf42db9315918f062
A6: 5 | B6: 2026-10-23 | C6: CRWV | D6: CoreWeave, Inc. | E6: CoreWeave債務壓力升溫 市值蒸發440億美元 | F6: CoreWeave 的債務壓力升溫，市值蒸發 440 億美元，顯示公司可能面臨流動性危機，但尚未確認違約或其他重大事件。 | G6: 鉅亨網 | I6: LIQUIDITY_CRISIS | J6: 流動性危機 | K6: 5 | L6: 維持 | N6: 低 | O6: 標題只說債務壓力升溫、市值蒸發 440 億美元，未見無法償付或融資中斷；若原文無流動性斷裂證據，建議降為 OPERATING_DETERIORATION。 | P6: 是 | Q6: 維持 | S6: =IF(Q6="維持",J6,IF(Q6="排除","無關新聞事件",IFERROR(INDEX(事件規則!$B$2:$B$53,MATCH(R6,事件規則!$A$2:$A$53,0)),""))) -> 流動性危機 | T6: =IF(Q6="維持",K6,IF(Q6="排除",0,IFERROR(INDEX(事件規則!$C$2:$C$53,MATCH(R6,事件規則!$A$2:$A$53,0)),""))) -> 5 | U6: =IF(AND(Q6="修改",R6=""),"請選新事件代碼",IF(AND(Q6<>"修改",R6<>""),"只有「修改」才需填代碼","")) | X6: 9f5e4c8fa92063aecb307529
A7: 6 | B7: 2026-10-22 | D7: RNDC | E7: RNDC Files for Chapter 11, Pursues Sales and Wind-Down | F7: RNDC 申請第 11 章破產，並計畫出售資產及逐步關閉營運。 | G7: National Association of Wholesaler-Distributors | I7: BANKRUPTCY | J7: 破產 | K7: 5 | L7: 維持 | N7: 中 | O7: RNDC 申請 Chapter 11 並出售資產、逐步關閉，事件屬實；但 RNDC 為未上市酒類經銷商，Ticker 空白，請確認是否屬監控對象。 | P7: 是 | Q7: 維持 | S7: =IF(Q7="維持",J7,IF(Q7="排除","無關新聞事件",IFERROR(INDEX(事件規則!$B$2:$B$53,MATCH(R7,事件規則!$A$2:$A$53,0)),""))) -> 破產 | T7: =IF(Q7="維持",K7,IF(Q7="排除",0,IFERROR(INDEX(事件規則!$C$2:$C$53,MATCH(R7,事件規則!$A$2:$A$53,0)),""))) -> 5 | U7: =IF(AND(Q7="修改",R7=""),"請選新事件代碼",IF(AND(Q7<>"修改",R7<>""),"只有「修改」才需填代碼","")) | X7: 5a0e0d95455677066de7d303
A8: 7 | B8: 2026-08-30 | D8: Apple Inc. | E8: 蘋果Siri功能跳票賠17億 | G8: TradingView | I8: DEFAULT | J8: 違約 | K8: 5 | L8: 修改 | M8: MAJOR_LITIGATION | N8: 中 | O8: 標題為蘋果 Siri 功能跳票賠償 17 億，屬訴訟和解，不是債務違約；金額與幣別未確認。 | P8: 是 | Q8: 修改 | R8: MAJOR_LITIGATION | S8: =IF(Q8="維持",J8,IF(Q8="排除","無關新聞事件",IFERROR(INDEX(事件規則!$B$2:$B$53,MATCH(R8,事件規則!$A$2:$A$53,0)),""))) -> 重大訴訟 | T8: =IF(Q8="維持",K8,IF(Q8="排除",0,IFERROR(INDEX(事件規則!$C$2:$C$53,MATCH(R8,事件規則!$A$2:$A$53,0)),""))) -> 4 | U8: =IF(AND(Q8="修改",R8=""),"請選新事件代碼",IF(AND(Q8<>"修改",R8<>""),"只有「修改」才需填代碼","")) | X8: e38e29eaf5c6faa3f5dcc44f
A9: 8 | B9: 2026-10-13 | D9: Walt Disney Company (The) | E9: Character.AI files for bankruptcy reorganization and agrees to sell some assets to Disney | F9: Character.AI 申請破產重組並同意將部分資產出售給迪士尼 | G9: TradingView | H9: -0.027 | I9: BANKRUPTCY | J9: 破產 | K9: 5 | L9: 排除 | N9: 中 | O9: 申請破產的是 Character.AI，Disney 只是資產買方，不是 Disney 本身的信用事件。 | Q9: 排除 | S9: =IF(Q9="維持",J9,IF(Q9="排除","無關新聞事件",IFERROR(INDEX(事件規則!$B$2:$B$53,MATCH(R9,事件規則!$A$2:$A$53,0)),""))) -> 無關新聞事件 | T9: =IF(Q9="維持",K9,IF(Q9="排除",0,IFERROR(INDEX(事件規則!$C$2:$C$53,MATCH(R9,事件規則!$A$2:$A$53,0)),""))) -> 0 | U9: =IF(AND(Q9="修改",R9=""),"請選新事件代碼",IF(AND(Q9<>"修改",R9<>""),"只有「修改」才需填代碼","")) | X9: d4871428d73a5f522ce6f6e8
A10: 9 | B10: 2026-08-11 | D10: Visa Inc. | E10: Client Alert: Subchapter V Surge: What Florida Trade Creditors and Lenders Need to Know About the New Small Business Bankruptcy Landscape | F10: 客戶警報：第五章激增：佛羅裡達州貿易債權人和貸款人需要了解新的小型企業破產情況 | G10: JD Supra | H10: -0.046 | I10: BANKRUPTCY | J10: 破產 | K10: 5 | L10: 排除 | N10: 高 | O10: JD Supra 律師事務所客戶通知，談佛州小型企業 Subchapter V 破產制度，與 Visa 無關。 | Q10: 排除 | S10: =IF(Q10="維持",J10,IF(Q10="排除","無關新聞事件",IFERROR(INDEX(事件規則!$B$2:$B$53,MATCH(R10,事件規則!$A$2:$A$53,0)),""))) -> 無關新聞事件 | T10: =IF(Q10="維持",K10,IF(Q10="排除",0,IFERROR(INDEX(事件規則!$C$2:$C$53,MATCH(R10,事件規則!$A$2:$A$53,0)),""))) -> 0 | U10: =IF(AND(Q10="修改",R10=""),"請選新事件代碼",IF(AND(Q10<>"修改",R10<>""),"只有「修改」才需填代碼","")) | X10: 12ad0d8ae11f6d17e1b235e4
A11: 10 | B11: 2026-08-14 | D11: Ameriprise Financial | E11: The TL072: A JFET Op Amp That Became the Default for Audio | F11: TL072：成為音訊預設的 JFET 運算放大器 | G11: All About Circuits | H11: 0.017 | I11: DEFAULT | J11: 違約 | K11: 5 | L11: 排除 | N11: 高 | O11: 文章談 TL072 運算放大器，「Default」是「預設」，不是違約。 | Q11: 排除 | S11: =IF(Q11="維持",J11,IF(Q11="排除","無關新聞事件",IFERROR(INDEX(事件規則!$B$2:$B$53,MATCH(R11,事件規則!$A$2:$A$53,0)),""))) -> 無關新聞事件 | T11: =IF(Q11="維持",K11,IF(Q11="排除",0,IFERROR(INDEX(事件規則!$C$2:$C$53,MATCH(R11,事件規則!$A$2:$A$53,0)),""))) -> 0 | U11: =IF(AND(Q11="修改",R11=""),"請選新事件代碼",IF(AND(Q11<>"修改",R11<>""),"只有「修改」才需填代碼","")) | X11: 7fb4ffc75dba5008caff4ea0
A12: 11 | B12: 2026-08-16 | D12: Intercontinental Exchange | E12: Major ice cream brand seeks Chapter 11 bankruptcy after lawsuit | F12: 大型冰淇淋品牌在訴訟後尋求美國破產法第11章破產保護 | G12: thestreet.com | H12: -0.876 | I12: BANKRUPTCY | J12: 破產 | K12: 5 | L12: 排除 | N12: 高 | O12: 破產的是未上市冰淇淋品牌（Rebel Creamery），與 Intercontinental Exchange 無關，公司比對錯誤。 | Q12: 排除 | S12: =IF(Q12="維持",J12,IF(Q12="排除","無關新聞事件",IFERROR(INDEX(事件規則!$B$2:$B$53,MATCH(R12,事件規則!$A$2:$A$53,0)),""))) -> 無關新聞事件 | T12: =IF(Q12="維持",K12,IF(Q12="排除",0,IFERROR(INDEX(事件規則!$C$2:$C$53,MATCH(R12,事件規則!$A$2:$A$53,0)),""))) -> 0 | U12: =IF(AND(Q12="修改",R12=""),"請選新事件代碼",IF(AND(Q12<>"修改",R12<>""),"只有「修改」才需填代碼","")) | X12: bc906869ade2807298deba23
A13: 12 | B13: 2026-08-16 | D13: Intercontinental Exchange | E13: Ice cream brand sold in Houston files for bankruptcy after Van Leeuwen lawsuit | F13: Van Leeuwen 提起訴訟後，休士頓銷售的冰淇淋品牌申請破產 | G13: Houston Chronicle | H13: -0.875 | I13: BANKRUPTCY | J13: 破產 | K13: 5 | L13: 排除 | N13: 高 | O13: 同上（Rebel Creamery 破產，與 ICE 無關）。 | Q13: 排除 | S13: =IF(Q13="維持",J13,IF(Q13="排除","無關新聞事件",IFERROR(INDEX(事件規則!$B$2:$B$53,MATCH(R13,事件規則!$A$2:$A$53,0)),""))) -> 無關新聞事件 | T13: =IF(Q13="維持",K13,IF(Q13="排除",0,IFERROR(INDEX(事件規則!$C$2:$C$53,MATCH(R13,事件規則!$A$2:$A$53,0)),""))) -> 0 | U13: =IF(AND(Q13="修改",R13=""),"請選新事件代碼",IF(AND(Q13<>"修改",R13<>""),"只有「修改」才需填代碼","")) | X13: a85ae63eb43f73633d49b45f
A14: 13 | B14: 2026-08-16 | D14: Intercontinental Exchange | E14: Maker of ice cream sold at grocery stores nationwide files for bankruptcy as it appeals $23.8M judgment | F14: 在全國雜貨店銷售的冰淇淋製造商申請破產，對 2,380 萬美元的判決提出上訴 | G14: Fox Business | H14: -0.923 | I14: BANKRUPTCY | J14: 破產 | K14: 5 | L14: 排除 | N14: 高 | O14: 同上（Rebel Creamery 破產，與 ICE 無關）。 | Q14: 排除 | S14: =IF(Q14="維持",J14,IF(Q14="排除","無關新聞事件",IFERROR(INDEX(事件規則!$B$2:$B$53,MATCH(R14,事件規則!$A$2:$A$53,0)),""))) -> 無關新聞事件 | T14: =IF(Q14="維持",K14,IF(Q14="排除",0,IFERROR(INDEX(事件規則!$C$2:$C$53,MATCH(R14,事件規則!$A$2:$A$53,0)),""))) -> 0 | U14: =IF(AND(Q14="修改",R14=""),"請選新事件代碼",IF(AND(Q14<>"修改",R14<>""),"只有「修改」才需填代碼","")) | X14: c102ff8d98a6d71791c190c6
A15: 14 | B15: 2026-08-17 | D15: Intercontinental Exchange | E15: Popular ice cream brand sold at Walmart and Target files for bankruptcy | F15: 沃爾瑪和塔吉特銷售的熱門冰淇淋品牌申請破產 | G15: Yahoo Finance | H15: -0.757 | I15: BANKRUPTCY | J15: 破產 | K15: 5 | L15: 排除 | N15: 高 | O15: 同上（Rebel Creamery 破產，與 ICE 無關）。 | Q15: 排除 | S15: =IF(Q15="維持",J15,IF(Q15="排除","無關新聞事件",IFERROR(INDEX(事件規則!$B$2:$B$53,MATCH(R15,事件規則!$A$2:$A$53,0)),""))) -> 無關新聞事件 | T15: =IF(Q15="維持",K15,IF(Q15="排除",0,IFERROR(INDEX(事件規則!$C$2:$C$53,MATCH(R15,事件規則!$A$2:$A$53,0)),""))) -> 0 | U15: =IF(AND(Q15="修改",R15=""),"請選新事件代碼",IF(AND(Q15<>"修改",R15<>""),"只有「修改」才需填代碼","")) | X15: 11dfdd497cf6d878e41e446f
A16: 15 | B16: 2026-08-17 | D16: Costco | E16: The mistake that helped cost Rebel Creamery $23.8 million and pushed it into bankruptcy | F16: 這一錯誤導致 Rebel Creamery 損失 2,380 萬美元，並導致其破產 | G16: Yahoo | H16: -0.919 | I16: BANKRUPTCY | J16: 破產 | K16: 5 | L16: 排除 | N16: 高 | O16: 破產的是 Rebel Creamery，Costco 只是賣場關聯，非 Costco 的信用事件。 | Q16: 排除 | S16: =IF(Q16="維持",J16,IF(Q16="排除","無關新聞事件",IFERROR(INDEX(事件規則!$B$2:$B$53,MATCH(R16,事件規則!$A$2:$A$53,0)),""))) -> 無關新聞事件 | T16: =IF(Q16="維持",K16,IF(Q16="排除",0,IFERROR(INDEX(事件規則!$C$2:$C$53,MATCH(R16,事件規則!$A$2:$A$53,0)),""))) -> 0 | U16: =IF(AND(Q16="修改",R16=""),"請選新事件代碼",IF(AND(Q16<>"修改",R16<>""),"只有「修改」才需填代碼","")) | X16: 4b684ac9d5af90e4b5ffdda5
A17: 16 | B17: 2026-08-15 | C17: WBD | D17: Warner Bros. Discovery | E17: Paramount-WBD Merger: David Ellison Complains About Cost Of States' Antitrust Suit | F17: 派拉蒙與 WBD 合併：大衛·埃里森抱怨各州反壟斷訴訟的成本 | G17: Deadline | H17: -0.929 | I17: ANTITRUST_INVESTIGATION | J17: 反壟斷調查 | K17: 4 | L17: 維持 | N17: 高 | O17: 派拉蒙併購 WBD 遭多州提出反壟斷訴訟。 | Q17: 維持 | S17: =IF(Q17="維持",J17,IF(Q17="排除","無關新聞事件",IFERROR(INDEX(事件規則!$B$2:$B$53,MATCH(R17,事件規則!$A$2:$A$53,0)),""))) -> 反壟斷調查 | T17: =IF(Q17="維持",K17,IF(Q17="排除",0,IFERROR(INDEX(事件規則!$C$2:$C$53,MATCH(R17,事件規則!$A$2:$A$53,0)),""))) -> 4 | U17: =IF(AND(Q17="修改",R17=""),"請選新事件代碼",IF(AND(Q17<>"修改",R17<>""),"只有「修改」才需填代碼","")) | X17: 7c7dddbb36f73ba60dc653c0
A18: 17 | B18: 2026-08-26 | C18: META | D18: Meta Platforms, Inc. | E18: Meta就多個州的致兒童成癮訴訟達成167億美元和解 | G18: TradingView | I18: MAJOR_LITIGATION | J18: 重大訴訟 | K18: 4 | L18: 維持 | N18: 高 | O18: Meta 就多州兒童成癮訴訟達成 167 億美元和解。 | Q18: 維持 | S18: =IF(Q18="維持",J18,IF(Q18="排除","無關新聞事件",IFERROR(INDEX(事件規則!$B$2:$B$53,MATCH(R18,事件規則!$A$2:$A$53,0)),""))) -> 重大訴訟 | T18: =IF(Q18="維持",K18,IF(Q18="排除",0,IFERROR(INDEX(事件規則!$C$2:$C$53,MATCH(R18,事件規則!$A$2:$A$53,0)),""))) -> 4 | U18: =IF(AND(Q18="修改",R18=""),"請選新事件代碼",IF(AND(Q18<>"修改",R18<>""),"只有「修改」才需填代碼","")) | X18: 9c0b1c683bbf8fe47bb8f5e6
A19: 18 | B19: 2026-10-09 | D19: American Express | E19: 美國運通因反洗錢計劃不完善被罰款3.5億美元 | G19: TradingView | H19: 0.028 | I19: REGULATORY_PENALTY | J19: 監管裁罰 | K19: 4 | L19: 維持 | N19: 高 | O19: 美國運通因反洗錢計畫缺失被罰 3.5 億美元；Ticker 空白，建議補 AXP。 | Q19: 維持 | S19: =IF(Q19="維持",J19,IF(Q19="排除","無關新聞事件",IFERROR(INDEX(事件規則!$B$2:$B$53,MATCH(R19,事件規則!$A$2:$A$53,0)),""))) -> 監管裁罰 | T19: =IF(Q19="維持",K19,IF(Q19="排除",0,IFERROR(INDEX(事件規則!$C$2:$C$53,MATCH(R19,事件規則!$A$2:$A$53,0)),""))) -> 4 | U19: =IF(AND(Q19="修改",R19=""),"請選新事件代碼",IF(AND(Q19<>"修改",R19<>""),"只有「修改」才需填代碼","")) | X19: ba7c5621b413520ed3012946
A20: 19 | B20: 2026-09-03 | D20: Boeing | E20: 波音因普遍存在的安全違規行為向美國聯邦航空管理局（FAA）支付了310萬美元罰款 | G20: TradingView | I20: REGULATORY_PENALTY | J20: 監管裁罰 | K20: 4 | L20: 維持 | N20: 高 | O20: 波音因安全違規向 FAA 支付 310 萬美元罰款；Ticker 空白，建議補 BA。 | Q20: 維持 | S20: =IF(Q20="維持",J20,IF(Q20="排除","無關新聞事件",IFERROR(INDEX(事件規則!$B$2:$B$53,MATCH(R20,事件規則!$A$2:$A$53,0)),""))) -> 監管裁罰 | T20: =IF(Q20="維持",K20,IF(Q20="排除",0,IFERROR(INDEX(事件規則!$C$2:$C$53,MATCH(R20,事件規則!$A$2:$A$53,0)),""))) -> 4 | U20: =IF(AND(Q20="修改",R20=""),"請選新事件代碼",IF(AND(Q20<>"修改",R20<>""),"只有「修改」才需填代碼","")) | X20: 8a311f19c6ae51248071cbc4
A21: 20 | B21: 2026-09-18 | D21: Corpay | E21: Corpay to Pay $100 Million to Resolve FTC Allegations | G21: Yahoo Finance | H21: 0.131 | I21: REGULATORY_INVESTIGATION | J21: 監管調查 | K21: 4 | L21: 修改 | M21: REGULATORY_PENALTY | N21: 中 | O21: Corpay 支付 1 億美元和解 FTC 指控，已是裁罰結果，不只是調查。 | Q21: 修改 | R21: REGULATORY_PENALTY | S21: =IF(Q21="維持",J21,IF(Q21="排除","無關新聞事件",IFERROR(INDEX(事件規則!$B$2:$B$53,MATCH(R21,事件規則!$A$2:$A$53,0)),""))) -> 監管裁罰 | T21: =IF(Q21="維持",K21,IF(Q21="排除",0,IFERROR(INDEX(事件規則!$C$2:$C$53,MATCH(R21,事件規則!$A$2:$A$53,0)),""))) -> 4 | U21: =IF(AND(Q21="修改",R21=""),"請選新事件代碼",IF(AND(Q21<>"修改",R21<>""),"只有「修改」才需填代碼","")) | X21: 769df537c0dad0a13fcbec07
A22: 21 | B22: 2026-10-24 | C22: GL | D22: Globe Life | E22: Globe Life shares fall 8% after outlook cut and downgrade | F22: Globe Life 股價因展望下調及信用評級下調而下跌 8%。 | G22: finchannel | H22: -0.964 | I22: CREDIT_DOWNGRADE | J22: 信用調降 | K22: 4 | L22: 修改 | M22: EARNINGS_WARNING | N22: 中 | O22: Globe Life 因下修展望與遭分析師降評，股價跌 8%；不是信用評等調降。 | Q22: 修改 | R22: EARNINGS_WARNING | S22: =IF(Q22="維持",J22,IF(Q22="排除","無關新聞事件",IFERROR(INDEX(事件規則!$B$2:$B$53,MATCH(R22,事件規則!$A$2:$A$53,0)),""))) -> 財測下修 | T22: =IF(Q22="維持",K22,IF(Q22="排除",0,IFERROR(INDEX(事件規則!$C$2:$C$53,MATCH(R22,事件規則!$A$2:$A$53,0)),""))) -> 3 | U22: =IF(AND(Q22="修改",R22=""),"請選新事件代碼",IF(AND(Q22<>"修改",R22<>""),"只有「修改」才需填代碼","")) | X22: 9041019a7c22ab6139fb54f9
A23: 22 | B23: 2026-10-21 | C23: YRD | D23: Yiren Digital Ltd. American Depositary S | E23: Securities Fraud Investigation Into Yiren Digital Ltd. (YRD) Cont | F23: 依據報導，Yiren Digital Ltd. (YRD) 正在接受證券詐欺調查，屬於監管調查事件。 | G23: The National Law Review | I23: REGULATORY_INVESTIGATION | J23: 監管調查 | K23: 4 | L23: 維持 | N23: 低 | O23: 疑似律師事務所代股東發出的「證券詐欺調查」公告，不是監管機關調查；若是，建議改 MAJOR_LITIGATION 或排除。 | P23: 是 | Q23: 維持 | S23: =IF(Q23="維持",J23,IF(Q23="排除","無關新聞事件",IFERROR(INDEX(事件規則!$B$2:$B$53,MATCH(R23,事件規則!$A$2:$A$53,0)),""))) -> 監管調查 | T23: =IF(Q23="維持",K23,IF(Q23="排除",0,IFERROR(INDEX(事件規則!$C$2:$C$53,MATCH(R23,事件規則!$A$2:$A$53,0)),""))) -> 4 | U23: =IF(AND(Q23="修改",R23=""),"請選新事件代碼",IF(AND(Q23<>"修改",R23<>""),"只有「修改」才需填代碼","")) | X23: 53452bb45fbda9cdb9797775
A24: 23 | B24: 2026-08-19 | D24: AppLovin | E24: Apple Changes App Store Terms to Resolve E.U. Antitrust Dispute | G24: Barron's | H24: -0.39 | I24: ANTITRUST_INVESTIGATION | J24: 反壟斷調查 | K24: 4 | L24: 維持 | N24: 低 | O24: 事件是 Apple 為化解歐盟反壟斷爭議調整 App Store 條款，但公司欄位為 AppLovin，疑似歸錯公司。 | P24: 是 | Q24: 維持 | S24: =IF(Q24="維持",J24,IF(Q24="排除","無關新聞事件",IFERROR(INDEX(事件規則!$B$2:$B$53,MATCH(R24,事件規則!$A$2:$A$53,0)),""))) -> 反壟斷調查 | T24: =IF(Q24="維持",K24,IF(Q24="排除",0,IFERROR(INDEX(事件規則!$C$2:$C$53,MATCH(R24,事件規則!$A$2:$A$53,0)),""))) -> 4 | U24: =IF(AND(Q24="修改",R24=""),"請選新事件代碼",IF(AND(Q24<>"修改",R24<>""),"只有「修改」才需填代碼","")) | X24: ee5754561338bdfca7341bae
A25: 24 | B25: 2026-10-24 | D25: 美國資料中心 | E25: 標普為AI債務危機「火上澆油」？示警美國資料中心信用降評風險 | F25: 標普為AI債務危機「火上澆油」？示警美國資料中心信用降評風險 | G25: 鉅亨網 | H25: -0.739 | I25: CREDIT_DOWNGRADE | J25: 信用調降 | K25: 4 | L25: 排除 | N25: 低 | O25: 標普示警的是資料中心產業的信用降評風險，公司欄為「美國資料中心」，不是特定公司。 | P25: 是 | Q25: 排除 | S25: =IF(Q25="維持",J25,IF(Q25="排除","無關新聞事件",IFERROR(INDEX(事件規則!$B$2:$B$53,MATCH(R25,事件規則!$A$2:$A$53,0)),""))) -> 無關新聞事件 | T25: =IF(Q25="維持",K25,IF(Q25="排除",0,IFERROR(INDEX(事件規則!$C$2:$C$53,MATCH(R25,事件規則!$A$2:$A$53,0)),""))) -> 0 | U25: =IF(AND(Q25="修改",R25=""),"請選新事件代碼",IF(AND(Q25<>"修改",R25<>""),"只有「修改」才需填代碼","")) | X25: 2f9132328e1a6e29bfc911ef
A26: 25 | B26: 2026-08-20 | C26: CME | D26: CME Group Inc. | E26: CME CEO Spars With CFTC Chair About Prediction Market Oversight | G26: Bloomberg.com | H26: -0.03 | I26: REGULATORY_INVESTIGATION | J26: 監管調查 | K26: 4 | L26: 排除 | N26: 中 | O26: CME 執行長與 CFTC 主席公開交鋒（預測市場監管），沒有調查或裁罰。 | Q26: 排除 | S26: =IF(Q26="維持",J26,IF(Q26="排除","無關新聞事件",IFERROR(INDEX(事件規則!$B$2:$B$53,MATCH(R26,事件規則!$A$2:$A$53,0)),""))) -> 無關新聞事件 | T26: =IF(Q26="維持",K26,IF(Q26="排除",0,IFERROR(INDEX(事件規則!$C$2:$C$53,MATCH(R26,事件規則!$A$2:$A$53,0)),""))) -> 0 | U26: =IF(AND(Q26="修改",R26=""),"請選新事件代碼",IF(AND(Q26<>"修改",R26<>""),"只有「修改」才需填代碼","")) | X26: 4ce2f2951b07ed8eb8da64ae
A27: 26 | B27: 2026-08-13 | C27: DUK | D27: Duke Energy | E27: Duke Energy cuts proposed rate hike nearly in half as NC regulators weigh settlement | F27: 北卡羅來納州監管機構考慮和解，杜克能源公司將升息提議削減近一半 | G27: WSPA 7News | H27: -0.888 | I27: REGULATORY_PENALTY | J27: 監管裁罰 | K27: 4 | L27: 排除 | N27: 高 | O27: 北卡州電價調漲案，Duke Energy 調降申請幅度，不是裁罰。 | Q27: 排除 | S27: =IF(Q27="維持",J27,IF(Q27="排除","無關新聞事件",IFERROR(INDEX(事件規則!$B$2:$B$53,MATCH(R27,事件規則!$A$2:$A$53,0)),""))) -> 無關新聞事件 | T27: =IF(Q27="維持",K27,IF(Q27="排除",0,IFERROR(INDEX(事件規則!$C$2:$C$53,MATCH(R27,事件規則!$A$2:$A$53,0)),""))) -> 0 | U27: =IF(AND(Q27="修改",R27=""),"請選新事件代碼",IF(AND(Q27<>"修改",R27<>""),"只有「修改」才需填代碼","")) | X27: fe69b51d84a7081e8d214db9
A28: 27 | B28: 2026-10-25 | C28: MCD | D28: McDonald's | E28: Latham McDonald's Grease Dump Draws DEC Investigation | F28: 麥當勞因油脂排放問題被美國環保署調查。 | G28: Hoodline | H28: -0.26 | I28: REGULATORY_INVESTIGATION | J28: 監管調查 | K28: 4 | L28: 排除 | N28: 中 | O28: 單一門市油脂排放遭州環保局調查，規模與集團信用無關。 | Q28: 排除 | S28: =IF(Q28="維持",J28,IF(Q28="排除","無關新聞事件",IFERROR(INDEX(事件規則!$B$2:$B$53,MATCH(R28,事件規則!$A$2:$A$53,0)),""))) -> 無關新聞事件 | T28: =IF(Q28="維持",K28,IF(Q28="排除",0,IFERROR(INDEX(事件規則!$C$2:$C$53,MATCH(R28,事件規則!$A$2:$A$53,0)),""))) -> 0 | U28: =IF(AND(Q28="修改",R28=""),"請選新事件代碼",IF(AND(Q28<>"修改",R28<>""),"只有「修改」才需填代碼","")) | X28: 13f18784179d9c781c259e85
A29: 28 | B29: 2026-08-15 | D29: KeyCorp | E29: Attorney General Jay Jones Announces Key Personnel Appointments | F29: 司法部長傑伊瓊斯宣布關鍵人員任命 | G29: Office of the Attorney General of Virginia | H29: -0.07 | I29: MAJOR_LITIGATION | J29: 重大訴訟 | K29: 4 | L29: 排除 | N29: 高 | O29: 維吉尼亞州檢察長人事任命公告，與 KeyCorp 無關。 | Q29: 排除 | S29: =IF(Q29="維持",J29,IF(Q29="排除","無關新聞事件",IFERROR(INDEX(事件規則!$B$2:$B$53,MATCH(R29,事件規則!$A$2:$A$53,0)),""))) -> 無關新聞事件 | T29: =IF(Q29="維持",K29,IF(Q29="排除",0,IFERROR(INDEX(事件規則!$C$2:$C$53,MATCH(R29,事件規則!$A$2:$A$53,0)),""))) -> 0 | U29: =IF(AND(Q29="修改",R29=""),"請選新事件代碼",IF(AND(Q29<>"修改",R29<>""),"只有「修改」才需填代碼","")) | X29: 03c1409f652a8600d1cad61e
A30: 29 | B30: 2026-08-28 | D30: Ford Motor Company | E30: Last minute penalty lifts Arkansas State women’s soccer past Stephen F. Austin | G30: K8 News | Jonesboro, Arkansas | H30: -0.059 | I30: REGULATORY_PENALTY | J30: 監管裁罰 | K30: 4 | L30: 排除 | N30: 高 | O30: 大學女子足球比賽罰球（penalty），與 Ford 無關。 | Q30: 排除 | S30: =IF(Q30="維持",J30,IF(Q30="排除","無關新聞事件",IFERROR(INDEX(事件規則!$B$2:$B$53,MATCH(R30,事件規則!$A$2:$A$53,0)),""))) -> 無關新聞事件 | T30: =IF(Q30="維持",K30,IF(Q30="排除",0,IFERROR(INDEX(事件規則!$C$2:$C$53,MATCH(R30,事件規則!$A$2:$A$53,0)),""))) -> 0 | U30: =IF(AND(Q30="修改",R30=""),"請選新事件代碼",IF(AND(Q30<>"修改",R30<>""),"只有「修改」才需填代碼","")) | X30: 44d610cecd4564b7ccd32929
A31: 30 | B31: 2026-10-24 | C31: PSA | D31: Public Storage | E31: FBI Officially Launch Investigation Into Massive Theft Of 6,451 PSA-Rated TCG Cards | F31: 美國聯邦調查局正式展開調查，針對大量盜取的 6,451 張 PSA 評級 TCG 卡片。 | G31: TheGamer | H31: -0.757 | I31: REGULATORY_INVESTIGATION | J31: 監管調查 | K31: 4 | L31: 排除 | N31: 高 | O31: FBI 調查的是 PSA 鑑定卡失竊案；PSA 指卡片鑑定公司，不是 Public Storage，Ticker 誤配。 | Q31: 排除 | S31: =IF(Q31="維持",J31,IF(Q31="排除","無關新聞事件",IFERROR(INDEX(事件規則!$B$2:$B$53,MATCH(R31,事件規則!$A$2:$A$53,0)),""))) -> 無關新聞事件 | T31: =IF(Q31="維持",K31,IF(Q31="排除",0,IFERROR(INDEX(事件規則!$C$2:$C$53,MATCH(R31,事件規則!$A$2:$A$53,0)),""))) -> 0 | U31: =IF(AND(Q31="修改",R31=""),"請選新事件代碼",IF(AND(Q31<>"修改",R31<>""),"只有「修改」才需填代碼","")) | X31: 630eed693f3793c4957828db

Sheet 事件規則
A1: Event_Code | B1: 事件中文 | C1: Level
A2: ACCOUNTING_FRAUD | B2: 會計舞弊 | C2: 5
A3: BANKRUPTCY | B3: 破產 | C3: 5
A4: DEFAULT | B4: 違約 | C4: 5
A5: DELISTING | B5: 下市 | C5: 5
A6: GOING_CONCERN | B6: 繼續經營疑慮 | C6: 5
A7: LIQUIDITY_CRISIS | B7: 流動性危機 | C7: 5
A8: TRADING_SUSPENSION | B8: 停牌 | C8: 5
A9: ANTITRUST_INVESTIGATION | B9: 反壟斷調查 | C9: 4
A10: AUDITOR_RESIGNATION | B10: 會計師辭任 | C10: 4
A11: CREDIT_DOWNGRADE | B11: 信用調降 | C11: 4
A12: ENVIRONMENTAL_INCIDENT | B12: 重大環境事故 | C12: 4
A13: EXECUTIVE_MISCONDUCT | B13: 高管不當行為 | C13: 4
... A53: UNKNOWN | B53: 待人工覆核 | C53: 0
A55: 來源：negative-news 的 Parameter_Event.xlsx（Event 工作表），2026-10-26 讀取。
