Workbook

Sheet 說明
A1: 負面新聞離線覆核：第二批（待人工覆核剩餘＋已分類 L3）
A2: 產生日期：2026-10-26 筆數：645（待人工覆核 315、已分類 L3 330）
A4: 怎麼填（只動黃色欄位）
A5: 1. 最終決定（R 欄）：已預填我的建議。維持＝沿用目前分類；修改＝改成「新事件代碼」；排除＝記為 NOT_RELEVANT、Level 0、Action「排除、不納入風險事件」。
A6: 2. 新事件代碼（S 欄）：只有「修改」才需要，從下拉選單選；新事件中文與新 Level 會自動帶出。
A7: 3. 更正公司（V 欄）、更正Ticker（W 欄）：只在公司歸屬錯誤或 Ticker 空白時填寫，空白代表不更正。已依 S&P 500 清單預填 Ticker 空白的列。
A8: 4. 覆核註記（Y 欄）、覆核人（Z 欄）：請填你的姓名；註記可空白。
A9: 5. 把握程度為「低」或「建議看原文」為「是」的列（紅字），建議點標題開原文確認。
A10: 6. 檢查欄（X）若出現紅字，表示該列填寫不完整。
A11: 7. 不要修改 news_id、人工版本欄；上傳時靠這兩欄對應與防衝突。
A12: 8. 確認後請另存為「檔名_已確認.xlsx」。
A14: 我的建議統計（即時計算）
A15: 建議維持： | B15: =COUNTIF(覆核!$M$2:$M$646,"維持") -> 173
A16: 建議修改： | B16: =COUNTIF(覆核!$M$2:$M$646,"修改") -> 22
A17: 建議排除： | B17: =COUNTIF(覆核!$M$2:$M$646,"排除") -> 450
A18: 最終決定尚未填寫的列數： | B18: =COUNTBLANK(覆核!$R$2:$R$646) -> 0
A20: 限制：我只看資料中的標題與摘要，沒有逐篇開原文；建議不保證全對，最終由你確認。Level 顏色：5 紅、4 橘、3 黃、2 淡藍、1 淺灰、0 深灰。

Sheet 覆核
A1: 序號 | B1: 日期 | C1: Ticker | D1: 公司 | E1: 標題（點擊開原文） | F1: 中文標題／摘要 | G1: 來源 | H1: FinBERT | I1: 目前事件代碼 | J1: 目前事件中文 | K1: 目前Level | L1: 目前分類狀態 | M1: 建議 | N1: 建議事件代碼 | O1: 把握程度 | P1: 理由 | Q1: 建議看原文 | R1: 最終決定 | S1: 新事件代碼 | T1: 新事件中文 | U1: 新Level | V1: 更正公司 | W1: 更正Ticker | X1: 檢查 | Y1: 覆核註記 | Z1: 覆核人 | AA1: news_id | AB1: 人工版本
A2: 1 | B2: 2026-10-23 | C2: CRWV | D2: CoreWeave, Inc. | E2: 股價月內跌36%、CDS利差飆升AI雲服務商CoreWeave(CRWV.US)深陷信心危機作者智通財經 | F2: CoreWeave 股價在一個月內下跌36%，同時其 CDS 利差急劇擴大，顯示市場對其信用風險的擔憂升高，但並未有任何明確的違約或破產訊息。 | G2: Investing.com 香港 - 股市報價& 財經新聞 | I2: CDS_SPREAD_WIDENING | J2: CDS利差擴大／信用風險升高 | K2: 3 | L2: 已分類 | M2: 維持 | O2: 高 | P2: CoreWeave 股價月內跌 36% 且 CDS 利差急升，市場對信用的信心下降。 | R2: 維持 | T2: =IF(R2="維持",J2,IF(R2="排除","無關新聞事件",IFERROR(INDEX(事件規則!$B$2:$B$53,MATCH(S2,事件規則!$A$2:$A$53,0)),""))) -> CDS利差擴大／信用風險升高 | U2: =IF(R2="維持",K2,IF(R2="排除",0,IFERROR(INDEX(事件規則!$C$2:$C$53,MATCH(S2,事件規則!$A$2:$A$53,0)),""))) -> 3 | X2: =IF(AND(R2="修改",S2=""),"請選新事件代碼",IF(AND(R2<>"修改",S2<>""),"只有「修改」才需填代碼","")) | AA2: a409987af5a8c21a78698323
A3: 2 | B3: 2026-10-23 | C3: CRWV | D3: CoreWeave, Inc. | E3: 股價月內跌36%、CDS利差飆升 AI雲服務商CoreWeave深陷信心危機 | F3: CoreWeave 股價在一個月內下跌36%，同時 CDS 利差急劇擴大，顯示市場對其信用風險的擔憂升高，但並未確認任何違約或其他重大事件。 | G3: Moomoo | I3: CDS_SPREAD_WIDENING | J3: CDS利差擴大／信用風險升高 | K3: 3 | L3: 已分類 | M3: 維持 | O3: 高 | P3: CoreWeave 股價月內跌 36% 且 CDS 利差急升，市場對信用的信心下降。 | R3: 維持 | T3: =IF(R3="維持",J3,IF(R3="排除","無關新聞事件",IFERROR(INDEX(事件規則!$B$2:$B$53,MATCH(S3,事件規則!$A$2:$A$53,0)),""))) -> CDS利差擴大／信用風險升高 | U3: =IF(R3="維持",K3,IF(R3="排除",0,IFERROR(INDEX(事件規則!$C$2:$C$53,MATCH(S3,事件規則!$A$2:$A$53,0)),""))) -> 3 | X3: =IF(AND(R3="修改",S3=""),"請選新事件代碼",IF(AND(R3<>"修改",S3<>""),"只有「修改」才需填代碼","")) | AA3: 2d665ff894609ba4dcbe3fbf
A4: 3 | B4: 2026-10-23 | C4: CRWV | D4: CoreWeave, Inc. | E4: CoreWeave Stock Tumbles as Bernstein Cuts Target on AI Debt Fears | F4: 核心算力公司CoreWeave因市場對其AI債務的擔憂，股價大幅下跌，顯示投資者對其信用風險的擔憂升高。 | G4: TradingView | I4: CDS_SPREAD_WIDENING | J4: CDS利差擴大／信用風險升高 | K4: 3 | L4: 已分類 | M4: 維持 | O4: 中 | P4: Bernstein 因 AI 債務疑慮調降 CoreWeave 目標價，股價下跌。 | R4: 維持 | T4: =IF(R4="維持",J4,IF(R4="排除","無關新聞事件",IFERROR(INDEX(事件規則!$B$2:$B$53,MATCH(S4,事件規則!$A$2:$A$53,0)),""))) -> CDS利差擴大／信用風險升高 | U4: =IF(R4="維持",K4,IF(R4="排除",0,IFERROR(INDEX(事件規則!$C$2:$C$53,MATCH(S4,事件規則!$A$2:$A$53,0)),""))) -> 3 | X4: =IF(AND(R4="修改",S4=""),"請選新事件代碼",IF(AND(R4<>"修改",S4<>""),"只有「修改」才需填代碼","")) | AA4: 13aeb2cf4e45fd614990924e
A5: 4 | B5: 2026-10-25 | C5: ADP | D5: Automatic Data Processing | E5: ADP implementation drops to 3.89pc in July-September | F5: 自動資料處理公司（ADP）在七至九月的實施率下降至3.89%，導致其信用違約掉期（CDS）利差擴大，顯示市場對其信用風險的擔憂升高。 | G5: The Financial Express | H5: -0.965 | I5: CDS_SPREAD_WIDENING | J5: CDS利差擴大／信用風險升高 | K5: 3 | L5: 已分類 | M5: 排除 | O5: 高 | P5: 文章談的是 ADP 實施率（與 Automatic Data Processing 無關）。 | R5: 排除 | T5: =IF(R5="維持",J5,IF(R5="排除","無關新聞事件",IFERROR(INDEX(事件規則!$B$2:$B$53,MATCH(S5,事件規則!$A$2:$A$53,0)),""))) -> 無關新聞事件 | U5: =IF(R5="維持",K5,IF(R5="排除",0,IFERROR(INDEX(事件規則!$C$2:$C$53,MATCH(S5,事件規則!$A$2:$A$53,0)),""))) -> 0 | X5: =IF(AND(R5="修改",S5=""),"請選新事件代碼",IF(AND(R5<>"修改",S5<>""),"只有「修改」才需填代碼","")) | AA5: 8a519af9cbc36c7c5948edab
A6: 5 | B6: 2026-08-09 | C6: MSFT | D6: Microsoft Corporation | E6: Microsoft releases Windows XP patch for WannaCrypt ransomware | F6: 微軟發布針對 WannaCrypt 勒索軟體的 Windows XP 補丁 | G6: Mashable | H6: -0.128 | I6: CYBER_ATTACK | J6: 資安攻擊 | K6: 3 | M6: 排除 | O6: 高 | P6: Windows XP WannaCrypt 修補程式為多年前舊聞，非新事件。 | R6: 排除 | T6: =IF(R6="維持",J6,IF(R6="排除","無關新聞事件",IFERROR(INDEX(事件規則!$B$2:$B$53,MATCH(S6,事件規則!$A$2:$A$53,0)),""))) -> 無關新聞事件 | U6: =IF(R6="維持",K6,IF(R6="排除",0,IFERROR(INDEX(事件規則!$C$2:$C$53,MATCH(S6,事件規則!$A$2:$A$53,0)),""))) -> 0 | X6: =IF(AND(R6="修改",S6=""),"請選新事件代碼",IF(AND(R6<>"修改",S6<>""),"只有「修改」才需填代碼","")) | AA6: 92d1743eeade3cb6fad4a889
A7: 6 | B7: 2026-08-10 | C7: MSFT | D7: Microsoft Corporation | E7: China-linked hackers turning popular cybersecurity tool into ransomware launchpad, Microsoft warns | F7: 微軟警告稱，與中國有關的駭客將流行的網路安全工具變成勒索軟體啟動板 | G7: The Record from Recorded Future News | H7: -0.078 | I7: CYBER_ATTACK | J7: 資安攻擊 | K7: 3 | M7: 排除 | O7: 中 | P7: Microsoft 是發出警告的一方，不是受害者。 | R7: 排除 | T7: =IF(R7="維持",J7,IF(R7="排除","無關新聞事件",IFERROR(INDEX(事件規則!$B$2:$B$53,MATCH(S7,事件規則!$A$2:$A$53,0)),""))) -> 無關新聞事件 | U7: =IF(R7="維持",K7,IF(R7="排除",0,IFERROR(INDEX(事件規則!$C$2:$C$53,MATCH(S7,事件規則!$A$2:$A$53,0)),""))) -> 0 | X7: =IF(AND(R7="修改",S7=""),"請選新事件代碼",IF(AND(R7<>"修改",S7<>""),"只有「修改」才需填代碼","")) | AA7: 988268a4ccf878c75da46a85
A8: 7 | B8: 2026-08-10 | C8: PSA | D8: Public Storage Common Stock | E8: PSA: Steam Machine and Steam Controller Customers in Europe Hit by Cyber Attack | F8: PSA：歐洲蒸汽機和蒸汽控制器客戶遭受網路攻擊 | G8: Digital Foundry | H8: -0.93 | I8: CYBER_ATTACK | J8: 資安攻擊 | K8: 3 | M8: 排除 | O8: 高 | P8: PSA 為「公共服務公告」，Steam 受攻擊與 Public Storage 無關。 | R8: 排除 | T8: =IF(R8="維持",J8,IF(R8="排除","無關新聞事件",IFERROR(INDEX(事件規則!$B$2:$B$53,MATCH(S8,事件規則!$A$2:$A$53,0)),""))) -> 無關新聞事件 | U8: =IF(R8="維持",K8,IF(R8="排除",0,IFERROR(INDEX(事件規則!$C$2:$C$53,MATCH(S8,事件規則!$A$2:$A$53,0)),""))) -> 0 | X8: =IF(AND(R8="修改",S8=""),"請選新事件代碼",IF(AND(R8<>"修改",S8<>""),"只有「修改」才需填代碼","")) | AA8: 408f0cdda38cf445ebf777d7
A9: 8 | B9: 2026-08-11 | C9: PSA | D9: Public Storage Common Stock | E9: PSA: Steam users have been hit by a cyber attack, ‘expect fake messages’ | F9: PSA：Steam 用戶遭受網路攻擊，“預計會出現虛假消息” | G9: Destructoid | H9: -0.922 | I9: CYBER_ATTACK | J9: 資安攻擊 | K9: 3 | M9: 排除 | O9: 高 | P9: PSA 為「公共服務公告」，Steam 受攻擊與 Public Storage 無關。 | R9: 排除 | T9: =IF(R9="維持",J9,IF(R9="排除","無關新聞事件",IFERROR(INDEX(事件規則!$B$2:$B$53,MATCH(S9,事件規則!$A$2:$A$53,0)),""))) -> 無關新聞事件 | U9: =IF(R9="維持",K9,IF(R9="排除",0,IFERROR(INDEX(事件規則!$C$2:$C$53,MATCH(S9,事件規則!$A$2:$A$53,0)),""))) -> 0 | X9: =IF(AND(R9="修改",S9=""),"請選新事件代碼",IF(AND(R9<>"修改",S9<>""),"只有「修改」才需填代碼","")) | AA9: 5aadece27ff463eaa8dce614
A10: 9 | B10: 2026-08-12 | C10: CRWD | D10: CrowdStrike | E10: AI驚傳脫序駭客事件！資安成下一波投資熱潮 專家點名 Palo Alto、CrowdStrike率先受惠 | F10: AI驚傳脫序駭客事件！資安成下一波投資熱潮 專家點名 Palo Alto、CrowdStrike率先受惠 | G10: 鉅亨網 | I10: CYBER_ATTACK | J10: 資安攻擊 | K10: 3 | M10: 排除 | O10: 高 | P10: 資安股投資評論／財報，不是這些公司遭攻擊。 | R10: 排除 | T10: =IF(R10="維持",J10,IF(R10="排除","無關新聞事件",IFERROR(INDEX(事件規則!$B$2:$B$53,MATCH(S10,事件規則!$A$2:$A$53,0)),""))) -> 無關新聞事件 | U10: =IF(R10="維持",K10,IF(R10="排除",0,IFERROR(INDEX(事件規則!$C$2:$C$53,MATCH(S10,事件規則!$A$2:$A$53,0)),""))) -> 0 | X10: =IF(AND(R10="修改",S10=""),"請選新事件代碼",IF(AND(R10<>"修改",S10<>""),"只有「修改」才需填代碼","")) | AA10: 02141c3c46d649e9c1225f18
A11: 10 | B11: 2026-09-02 | C11: PANW | D11: Palo Alto Networks, Inc. | E11: AI資安需求升温，Palo Alto Networks Q4業績及指引均勝預期 | G11: TradingView | I11: CYBER_ATTACK | J11: 資安攻擊 | K11: 3 | M11: 排除 | O11: 高 | P11: 資安股投資評論／財報，不是這些公司遭攻擊。 | R11: 排除 | T11: =IF(R11="維持",J11,IF(R11="排除","無關新聞事件",IFERROR(INDEX(事件規則!$B$2:$B$53,MATCH(S11,事件規則!$A$2:$A$53,0)),""))) -> 無關新聞事件 | U11: =IF(R11="維持",K11,IF(R11="排除",0,IFERROR(INDEX(事件規則!$C$2:$C$53,MATCH(S11,事件規則!$A$2:$A$53,0)),""))) -> 0 | X11: =IF(AND(R11="修改",S11=""),"請選新事件代碼",IF(AND(R11<>"修改",S11<>""),"只有「修改」才需填代碼","")) | AA11: 604f5199f8da58eb0972fb4b
A12: 11 | B12: 2026-09-09 | C12: T | D12: AT&T Inc. | E12: Iranian group claims responsibility for AT&T cyber attack | G12: FOX 4 News Dallas-Fort Worth | H12: -0.49 | I12: CYBER_ATTACK | J12: 資安攻擊 | K12: 3 | M12: 維持 | O12: 中 | P12: 伊朗組織宣稱對 AT&T 發動網路攻擊；屬對方宣稱，尚待證實。 | R12: 維持 | T12: =IF(R12="維持",J12,IF(R12="排除","無關新聞事件",IFERROR(INDEX(事件規則!$B$2:$B$53,MATCH(S12,事件規則!$A$2:$A$53,0)),""))) -> 資安攻擊 | U12: =IF(R12="維持",K12,IF(R12="排除",0,IFERROR(INDEX(事件規則!$C$2:$C$53,MATCH(S12,事件規則!$A$2:$A$53,0)),""))) -> 3 | X12: =IF(AND(R12="修改",S12=""),"請選新事件代碼",IF(AND(R12<>"修改",S12<>""),"只有「修改」才需填代碼","")) | AA12: 56a8e6d9f7d9285ccbceac4d
A13: 12 | B13: 2026-09-10 | C13: CSCO | D13: Cisco | E13: Cisco FMC bugs exploited by nation-state and ransomware actors (CVE-2026-20079, CVE-2026-20316) | G13: Help Net Security | H13: -0.572 | I13: CYBER_ATTACK | J13: 資安攻擊 | K13: 3 | M13: 維持 | O13: 中 | P13: Cisco FMC 軟體漏洞被國家級與勒索軟體組織利用，屬產品瑕疵，Cisco 本身未被入侵。 | R13: 維持 | T13: =IF(R13="維持",J13,IF(R13="排除","無關新聞事件",IFERROR(INDEX(事件規則!$B$2:$B$53,MATCH(S13,事件規則!$A$2:$A$53,0)),""))) -> 資安攻擊 | U13: =IF(R13="維持",K13,IF(R13="排除",0,IFERROR(INDEX(事件規則!$C$2:$C$53,MATCH(S13,事件規則!$A$2:$A$53,0)),""))) -> 3 | X13: =IF(AND(R13="修改",S13=""),"請選新事件代碼",IF(AND(R13<>"修改",S13<>""),"只有「修改」才需填代碼","")) | AA13: 6d8450cf1d2478dab7cfdd9a
A14: 13 | B14: 2026-09-11 | C14: CSCO | D14: Cisco | E14: Cisco FMC Flaws Exploited to Steal Credentials and Deploy Qilin Ransomware | G14: The Hacker News | H14: -0.751 | I14: CYBER_ATTACK | J14: 資安攻擊 | K14: 3 | M14: 維持 | O14: 中 | P14: Cisco FMC 軟體漏洞被國家級與勒索軟體組織利用，屬產品瑕疵，Cisco 本身未被入侵。 | R14: 維持 | T14: =IF(R14="維持",J14,IF(R14="排除","無關新聞事件",IFERROR(INDEX(事件規則!$B$2:$B$53,MATCH(S14,事件規則!$A$2:$A$53,0)),""))) -> 資安攻擊 | U14: =IF(R14="維持",K14,IF(R14="排除",0,IFERROR(INDEX(事件規則!$C$2:$C$53,MATCH(S14,事件規則!$A$2:$A$53,0)),""))) -> 3 | X14: =IF(AND(R14="修改",S14=""),"請選新事件代碼",IF(AND(R14<>"修改",S14<>""),"只有「修改」才需填代碼","")) | AA14: acb74955c92e417543c27e22
A15: 14 | B15: 2026-10-07 | C15: BA | D15: Boeing | E15: Ransomware gang targets FlyDubai - and says it has Boeing's code | G15: Insurance Business | H15: -0.304 | I15: CYBER_ATTACK | J15: 資安攻擊 | K15: 3 | M15: 維持 | O15: 中 | P15: 勒索軟體組織宣稱透過 FlyDubai 取得波音程式碼；屬對方宣稱。 | R15: 維持 | T15: =IF(R15="維持",J15,IF(R15="排除","無關新聞事件",IFERROR(INDEX(事件規則!$B$2:$B$53,MATCH(S15,事件規則!$A$2:$A$53,0)),""))) -> 資安攻擊 | U15: =IF(R15="維持",K15,IF(R15="排除",0,IFERROR(INDEX(事件規則!$C$2:$C$53,MATCH(S15,事件規則!$A$2:$A$53,0)),""))) -> 3 | X15: =IF(AND(R15="修改",S15=""),"請選新事件代碼",IF(AND(R15<>"修改",S15<>""),"只有「修改」才需填代碼","")) | AA15: c4048d11214374f0ea66a073
A16: 15 | B16: 2026-10-09 | C16: BA | D16: Boeing | E16: Flydubai and Boeing: Targets of Everest Ransomware Campaign | G16: Cyber Magazine | H16: -0.016 | I16: CYBER_ATTACK | J16: 資安攻擊 | K16: 3 | M16: 維持 | O16: 中 | P16: 勒索軟體組織宣稱透過 FlyDubai 取得波音程式碼；屬對方宣稱。 | R16: 維持 | T16: =IF(R16="維持",J16,IF(R16="排除","無關新聞事件",IFERROR(INDEX(事件規則!$B$2:$B$53,MATCH(S16,事件規則!$A$2:$A$53,0)),""))) -> 資安攻擊 | U16: =IF(R16="維持",K16,IF(R16="排除",0,IFERROR(INDEX(事件規則!$C$2:$C$53,MATCH(S16,事件規則!$A$2:$A$53,0)),""))) -> 3 | X16: =IF(AND(R16="修改",S16=""),"請選新事件代碼",IF(AND(R16<>"修改",S16<>""),"只有「修改」才需填代碼","")) | AA16: 07b4a0c0b95defc58dd555c3
A17: 16 | B17: 2026-08-13 | C17: UBER | D17: Uber Technologies, Inc. Common Stock | E17: Uber Freight reportedly investigating after hacking group claims data breach | F17: 據報道，Uber Freight 在駭客組織聲稱資料外洩後正在進行調查 | G17: TechCrunch | H17: -0.925 | I17: DATA_BREACH | J17: 資料外洩 | K17: 3 | M17: 維持 | O17: 中 | P17: 駭客組織宣稱入侵 Uber Freight，公司調查中。 | R17: 維持 | T17: =IF(R17="維持",J17,IF(R17="排除","無關新聞事件",IFERROR(INDEX(事件規則!$B$2:$B$53,MATCH(S17,事件規則!$A$2:$A$53,0)),""))) -> 資料外洩 | U17: =IF(R17="維持",K17,IF(R17="排除",0,IFERROR(INDEX(事件規則!$C$2:$C$53,MATCH(S17,事件規則!$A$2:$A$53,0)),""))) -> 3 | X17: =IF(AND(R17="修改",S17=""),"請選新事件代碼",IF(AND(R17<>"修改",S17<>""),"只有「修改」才需填代碼","")) | AA17: dd7f2946f86b0678ab55f27b
A18: 17 | B18: 2026-08-14 | C18: CRM | D18: Salesforce, Inc. Common Stock | E18: Over 1,000 Charities Hit by Beacon CRM Data Breach | F18: 超過 1,000 個慈善機構受到 Beacon CRM 資料外洩的影響 | G18: SecurityWeek | H18: -0.938 | I18: DATA_BREACH | J18: 資料外洩 | K18: 3 | M18: 排除 | O18: 高 | P18: Beacon CRM 是另一家供應商，非 Salesforce。 | R18: 排除 | T18: =IF(R18="維持",J18,IF(R18="排除","無關新聞事件",IFERROR(INDEX(事件規則!$B$2:$B$53,MATCH(S18,事件規則!$A$2:$A$53,0)),""))) -> 無關新聞事件 | U18: =IF(R18="維持",K18,IF(R18="排除",0,IFERROR(INDEX(事件規則!$C$2:$C$53,MATCH(S18,事件規則!$A$2:$A$53,0)),""))) -> 0 | X18: =IF(AND(R18="修改",S18=""),"請選新事件代碼",IF(AND(R18<>"修改",S18<>""),"只有「修改」才需填代碼","")) | AA18: 63e55ad1310d4ec1dd5066ec
A19: 18 | B19: 2026-08-15 | C19: LEN | D19: Lennar Corporation Class A Common Stock | E19: Lennar Corporation Data Breach Alert: Edelson Lechtzin LLP Launches Investigation Into Exposure of Personal Information | F19: Lennar Corporation 資料外洩警報：Edelson Lechtzin LLP 啟動針對個人資訊外洩的調查 | G19: The Daily Tribune News | H19: -0.591 | I19: DATA_BREACH | J19: 資料外洩 | K19: 3 | M19: 排除 | O19: 中 | P19: 律師事務所對 Lennar 資料外洩的徵求公告，事件已有其他報導。 | R19: 排除 | T19: =IF(R19="維持",J19,IF(R19="排除","無關新聞事件",IFERROR(INDEX(事件規則!$B$2:$B$53,MATCH(S19,事件規則!$A$2:$A$53,0)),""))) -> 無關新聞事件 | U19: =IF(R19="維持",K19,IF(R19="排除",0,IFERROR(INDEX(事件規則!$C$2:$C$53,MATCH(S19,事件規則!$A$2:$A$53,0)),""))) -> 0 | X19: =IF(AND(R19="修改",S19=""),"請選新事件代碼",IF(AND(R19<>"修改",S19<>""),"只有「修改」才需填代碼","")) | AA19: 4fcff80cbae75add25c9574a
A20: 19 | B20: 2026-08-15 | C20: LEN | D20: Lennar Corporation Class A Common Stock | E20: Lennar Corporation Data Breach Alert: Edelson Lechtzin LLP | F20: Lennar 公司資料外洩警報：Edelson Lechtzin LLP | G20: GlobeNewswire | H20: -0.07 | I20: DATA_BREACH | J20: 資料外洩 | K20: 3 | M20: 排除 | O20: 中 | P20: 律師事務所對 Lennar 資料外洩的徵求公告，事件已有其他報導。 | R20: 排除 | T20: =IF(R20="維持",J20,IF(R20="排除","無關新聞事件",IFERROR(INDEX(事件規則!$B$2:$B$53,MATCH(S20,事件規則!$A$2:$A$53,0)),""))) -> 無關新聞事件 | U20: =IF(R20="維持",K20,IF(R20="排除",0,IFERROR(INDEX(事件規則!$C$2:$C$53,MATCH(S20,事件規則!$A$2:$A$53,0)),""))) -> 0 | X20: =IF(AND(R20="修改",S20=""),"請選新事件代碼",IF(AND(R20<>"修改",S20<>""),"只有「修改」才需填代碼","")) | AA20: 1afc9ccb94eb0aab4b6f9d71
A21: 20 | B21: 2026-08-15 | C21: LEN | D21: Lennar Corporation Class A Common Stock | E21: Lennar Mortgage Data Breach Lawsuit Investigation | F21: Lennar 抵押貸款資料外洩訴訟調查 | G21: Claim Depot | H21: -0.859 | I21: DATA_BREACH | J21: 資料外洩 | K21: 3 | M21: 排除 | O21: 中 | P21: 律師事務所對 Lennar 資料外洩的徵求公告，事件已有其他報導。 | R21: 排除 | T21: =IF(R21="維持",J21,IF(R21="排除","無關新聞事件",IFERROR(INDEX(事件規則!$B$2:$B$53,MATCH(S21,事件規則!$A$2:$A$53,0)),""))) -> 無關新聞事件 | U21: =IF(R21="維持",K21,IF(R21="排除",0,IFERROR(INDEX(事件規則!$C$2:$C$53,MATCH(S21,事件規則!$A$2:$A$53,0)),""))) -> 0 | X21: =IF(AND(R21="修改",S21=""),"請選新事件代碼",IF(AND(R21<>"修改",S21<>""),"只有「修改」才需填代碼","")) | AA21: 3369449d738b1f178a63c13a
A22: 21 | B22: 2026-08-15 | C22: LEN | D22: Lennar Corporation Class A Common Stock | E22: Lennar Mortgage Data Breach Affects 60,526 Texans | F22: Lennar 抵押貸款資料外洩影響 60,526 名德州人 | G22: Claim Depot | H22: -0.333 | I22: DATA_BREACH | J22: 資料外洩 | K22: 3 | M22: 維持 | O22: 高 | P22: Lennar Mortgage 資料外洩，影響 60,526 名德州居民（含相關訴訟）。 | R22: 維持 | T22: =IF(R22="維持",J22,IF(R22="排除","無關新聞事件",IFERROR(INDEX(事件規則!$B$2:$B$53,MATCH(S22,事件規則!$A$2:$A$53,0)),""))) -> 資料外洩 | U22: =IF(R22="維持",K22,IF(R22="排除",0,IFERROR(INDEX(事件規則!$C$2:$C$53,MATCH(S22,事件規則!$A$2:$A$53,0)),""))) -> 3 | X22: =IF(AND(R22="修改",S22=""),"請選新事件代碼",IF(AND(R22<>"修改",S22<>""),"只有「修改」才需填代碼","")) | AA22: 594eaa985b351c2648b735eb
A23: 22 | B23: 2026-08-16 | C23: DOW | D23: Dow Inc. Common Stock | E23: Bloomberg Money Minute: Dow Hits Record High As SpaceX Plunges Canada Revenue Agency Data Breaches (Kz5b0Hg4QP) | F23: 彭博財經紀要：隨著 SpaceX 暴跌，道瓊指數創下歷史新高 加拿大稅務局資料外洩 (Kz5b0Hg4QP) | G23: Mshale | H23: 0.197 | I23: DATA_BREACH | J23: 資料外洩 | K23: 3 | M23: 排除 | O23: 高 | P23: Bloomberg 市場快報標題，資料外洩指加拿大稅務局，與 Dow 無關。 | R23: 排除 | T23: =IF(R23="維持",J23,IF(R23="排除","無關新聞事件",IFERROR(INDEX(事件規則!$B$2:$B$53,MATCH(S23,事件規則!$A$2:$A$53,0)),""))) -> 無關新聞事件 | U23: =IF(R23="維持",K23,IF(R23="排除",0,IFERROR(INDEX(事件規則!$C$2:$C$53,MATCH(S23,事件規則!$A$2:$A$53,0)),""))) -> 0 | X23: =IF(AND(R23="修改",S23=""),"請選新事件代碼",IF(AND(R23<>"修改",S23<>""),"只有「修改」才需填代碼","")) | AA23: 7031ef56aea01413bbc14779
A24: 23 | B24: 2026-08-17 | C24: IBM | D24: International Business Machines Corporat | E24: IBM: ASEAN data breach costs hit record US$4.12 million as AI attacks rise | F24: IBM：隨著人工智慧攻擊的增加，東協資料外洩成本達到創紀錄的 412 萬美元 | G24: crnasia.com | H24: 0.306 | I24: DATA_BREACH | J24: 資料外洩 | K24: 3 | M24: 排除 | O24: 高 | P24: IBM 發布的資料外洩成本報告，不是 IBM 自身事件。 | R24: 排除 | T24: =IF(R24="維持",J24,IF(R24="排除","無關新聞事件",IFERROR(INDEX(事件規則!$B$2:$B$53,MATCH(S24,事件規則!$A$2:$A$53,0)),""))) -> 無關新聞事件 | U24: =IF(R24="維持",K24,IF(R24="排除",0,IFERROR(INDEX(事件規則!$C$2:$C$53,MATCH(S24,事件規則!$A$2:$A$53,0)),""))) -> 0 | X24: =IF(AND(R24="修改",S24=""),"請選新事件代碼",IF(AND(R24<>"修改",S24<>""),"只有「修改」才需填代碼","")) | AA24: 9cecc970db7ffabca16030b6
A25: 24 | B25: 2026-08-19 | C25: LEN | D25: Lennar Corporation Class A Common Stock | E25: News - Lennar Mortgage data breach exposes personal information of more than 60,000 Texans | G25: teiss | H25: -0.926 | I25: DATA_BREACH | J25: 資料外洩 | K25: 3 | M25: 維持 | O25: 高 | P25: Lennar Mortgage 資料外洩，影響 60,526 名德州居民（含相關訴訟）。 | R25: 維持 | T25: =IF(R25="維持",J25,IF(R25="排除","無關新聞事件",IFERROR(INDEX(事件規則!$B$2:$B$53,MATCH(S25,事件規則!$A$2:$A$53,0)),""))) -> 資料外洩 | U25: =IF(R25="維持",K25,IF(R25="排除",0,IFERROR(INDEX(事件規則!$C$2:$C$53,MATCH(S25,事件規則!$A$2:$A$53,0)),""))) -> 3 | X25: =IF(AND(R25="修改",S25=""),"請選新事件代碼",IF(AND(R25<>"修改",S25<>""),"只有「修改」才需填代碼","")) | AA25: 98248d8bb5062e16bbdce959
A26: 25 | B26: 2026-08-20 | C26: CTSH | D26: Cognizant | E26: Cognizant Data Breach Lawsuit Investigation | G26: Claim Depot | H26: -0.767 | I26: DATA_BREACH | J26: 資料外洩 | K26: 3 | M26: 維持 | O26: 低 | P26: 「Cognizant 資料外洩訴訟調查」，內容僅為標題，請看原文確認是否有實際外洩。 | Q26: 是 | R26: 維持 | T26: =IF(R26="維持",J26,IF(R26="排除","無關新聞事件",IFERROR(INDEX(事件規則!$B$2:$B$53,MATCH(S26,事件規則!$A$2:$A$53,0)),""))) -> 資料外洩 | U26: =IF(R26="維持",K26,IF(R26="排除",0,IFERROR(INDEX(事件規則!$C$2:$C$53,MATCH(S26,事件規則!$A$2:$A$53,0)),""))) -> 3 | X26: =IF(AND(R26="修改",S26=""),"請選新事件代碼",IF(AND(R26<>"修改",S26<>""),"只有「修改」才需填代碼","")) | AA26: 3d33575d263b136c4a43c7fa
A27: 26 | B27: 2026-08-20 | C27: IBM | D27: International Business Machines Corporat | E27: IBM’s 2026 Data Breach Report: Houston, We Have A Problem | G27: Above the Law | H27: -0.946 | I27: DATA_BREACH | J27: 資料外洩 | K27: 3 | M27: 排除 | O27: 高 | P27: IBM 發布的資料外洩成本報告，不是 IBM 自身事件。 | R27: 排除 | T27: =IF(R27="維持",J27,IF(R27="排除","無關新聞事件",IFERROR(INDEX(事件規則!$B$2:$B$53,MATCH(S27,事件規則!$A$2:$A$53,0)),""))) -> 無關新聞事件 | U27: =IF(R27="維持",K27,IF(R27="排除",0,IFERROR(INDEX(事件規則!$C$2:$C$53,MATCH(S27,事件規則!$A$2:$A$53,0)),""))) -> 0 | X27: =IF(AND(R27="修改",S27=""),"請選新事件代碼",IF(AND(R27<>"修改",S27<>""),"只有「修改」才需填代碼","")) | AA27: b5fb7ce9cc34eee18630b78a
A28: 27 | B28: 2026-08-21 | C28: APO | D28: Apollo Global Management | E28: Apollo Global Management Data Breach Impacts SSNs; Lawsuit Possible | G28: classaction.org | H28: -0.933 | I28: DATA_BREACH | J28: 資料外洩 | K28: 3 | M28: 維持 | O28: 中 | P28: Apollo 資料外洩涉及社會安全號碼，可能提起訴訟。 | R28: 維持 | T28: =IF(R28="維持",J28,IF(R28="排除","無關新聞事件",IFERROR(INDEX(事件規則!$B$2:$B$53,MATCH(S28,事件規則!$A$2:$A$53,0)),""))) -> 資料外洩 | U28: =IF(R28="維持",K28,IF(R28="排除",0,IFERROR(INDEX(事件規則!$C$2:$C$53,MATCH(S28,事件規則!$A$2:$A$53,0)),""))) -> 3 | X28: =IF(AND(R28="修改",S28=""),"請選新事件代碼",IF(AND(R28<>"修改",S28<>""),"只有「修改」才需填代碼","")) | AA28: 95def5878b484fab12e3ab5e
A29: 28 | B29: 2026-09-03 | C29: DVA | D29: DaVita Inc. Common Stock | E29: DaVita agrees to pay $15M to settle claims from data breach | G29: Healthcare Dive | H29: 0.515 | I29: DATA_BREACH | J29: 資料外洩 | K29: 3 | M29: 維持 | O29: 高 | P29: DaVita 以 1,500 萬美元和解資料外洩索賠。 | R29: 維持 | T29: =IF(R29="維持",J29,IF(R29="排除","無關新聞事件",IFERROR(INDEX(事件規則!$B$2:$B$53,MATCH(S29,事件規則!$A$2:$A$53,0)),""))) -> 資料外洩 | U29: =IF(R29="維持",K29,IF(R29="排除",0,IFERROR(INDEX(事件規則!$C$2:$C$53,MATCH(S29,事件規則!$A$2:$A$53,0)),""))) -> 3 | X29: =IF(AND(R29="修改",S29=""),"請選新事件代碼",IF(AND(R29<>"修改",S29<>""),"只有「修改」才需填代碼","")) | AA29: a18c5f8cc1d23cf00e4d9c8a
A30: 29 | B30: 2026-09-08 | C30: LEN | D30: Lennar Corporation Class A Common Stock | E30: Lennar data breach lawsuit takes aim at company’s lax data security | G30: Top Class Actions | H30: -0.893 | I30: DATA_BREACH | J30: 資料外洩 | K30: 3 | M30: 維持 | O30: 高 | P30: Lennar Mortgage 資料外洩，影響 60,526 名德州居民（含相關訴訟）。 | R30: 維持 | T30: =IF(R30="維持",J30,IF(R30="排除","無關新聞事件",IFERROR(INDEX(事件規則!$B$2:$B$53,MATCH(S30,事件規則!$A$2:$A$53,0)),""))) -> 資料外洩 | U30: =IF(R30="維持",K30,IF(R30="排除",0,IFERROR(INDEX(事件規則!$C$2:$C$53,MATCH(S30,事件規則!$A$2:$A$53,0)),""))) -> 3 | X30: =IF(AND(R30="修改",S30=""),"請選新事件代碼",IF(AND(R30<>"修改",S30<>""),"只有「修改」才需填代碼","")) | AA30: 684239e1c4e7e3d7964a7f70
A31: 30 | B31: 2026-09-17 | C31: IBM | D31: International Business Machines Corporat | E31: IBM, J&J Get Incurable Data Breach Suit Tossed For Good | G31: Law360 | H31: -0.72 | I31: DATA_BREACH | J31: 資料外洩 | K31: 3 | M31: 排除 | O31: 中 | P31: IBM、J&J 的資料外洩訴訟被永久駁回，對公司為正面。 | R31: 排除 | T31: =IF(R31="維持",J31,IF(R31="排除","無關新聞事件",IFERROR(INDEX(事件規則!$B$2:$B$53,MATCH(S31,事件規則!$A$2:$A$53,0)),""))) -> 無關新聞事件 | U31: =IF(R31="維持",K31,IF(R31="排除",0,IFERROR(INDEX(事件規則!$C$2:$C$53,MATCH(S31,事件規則!$A$2:$A$53,0)),""))) -> 0 | X31: =IF(AND(R31="修改",S31=""),"請選新事件代碼",IF(AND(R31<>"修改",S31<>""),"只有「修改」才需填代碼","")) | AA31: 6ce8773304d44f52a85c5ca6
A32: 31 | B32: 2026-09-25 | C32: LH | D32: Labcorp | E32: Labcorp Settles Multistate Data Breach Investigation for $2.3 Million | G32: The HIPAA Journal | H32: -0.147 | I32: DATA_BREACH | J32: 資料外洩 | K32: 3 | M32: 維持 | O32: 高 | P32: Labcorp 以 230 萬美元和解多州資料外洩調查。 | R32: 維持 | T32: =IF(R32="維持",J32,IF(R32="排除","無關新聞事件",IFERROR(INDEX(事件規則!$B$2:$B$53,MATCH(S32,事件規則!$A$2:$A$53,0)),""))) -> 資料外洩 | U32: =IF(R32="維持",K32,IF(R32="排除",0,IFERROR(INDEX(事件規則!$C$2:$C$53,MATCH(S32,事件規則!$A$2:$A$53,0)),""))) -> 3 | X32: =IF(AND(R32="修改",S32=""),"請選新事件代碼",IF(AND(R32<>"修改",S32<>""),"只有「修改」才需填代碼","")) | AA32: 23ba8f3784dba1f0cb7e8c17
A33: 32 | B33: 2026-10-05 | C33: ACN | D33: Accenture plc Class A Ordinary Shares (I | E33: EXCLUSIVE: Accenture contractor removed from FBI following damaging data breach, sources say | G33: Reuters | H33: -0.936 | I33: DATA_BREACH | J33: 資料外洩 | K33: 3 | M33: 維持 | O33: 高 | P33: FBI 因資料外洩與未修補漏洞，終止與 Accenture 承包商合作。 | R33: 維持 | T33: =IF(R33="維持",J33,IF(R33="排除","無關新聞事件",IFERROR(INDEX(事件規則!$B$2:$B$53,MATCH(S33,事件規則!$A$2:$A$53,0)),""))) -> 資料外洩 | U33: =IF(R33="維持",K33,IF(R33="排除",0,IFERROR(INDEX(事件規則!$C$2:$C$53,MATCH(S33,事件規則!$A$2:$A$53,0)),""))) -> 3 | X33: =IF(AND(R33="修改",S33=""),"請選新事件代碼",IF(AND(R33<>"修改",S33<>""),"只有「修改」才需填代碼","")) | AA33: 0c94db61ca0b7844387a6c13
A34: 33 | B34: 2026-10-06 | C34: ACN | D34: Accenture plc Class A Ordinary Shares (I | E34: FBI Cuts Ties With Accenture After Missed Security Patch Linked To Data Breach | G34: LinkedIn | H34: -0.932 | I34: DATA_BREACH | J34: 資料外洩 | K34: 3 | M34: 維持 | O34: 高 | P34: FBI 因資料外洩與未修補漏洞，終止與 Accenture 承包商合作。 | R34: 維持 | T34: =IF(R34="維持",J34,IF(R34="排除","無關新聞事件",IFERROR(INDEX(事件規則!$B$2:$B$53,MATCH(S34,事件規則!$A$2:$A$53,0)),""))) -> 資料外洩 | U34: =IF(R34="維持",K34,IF(R34="排除",0,IFERROR(INDEX(事件規則!$C$2:$C$53,MATCH(S34,事件規則!$A$2:$A$53,0)),""))) -> 3 | X34: =IF(AND(R34="修改",S34=""),"請選新事件代碼",IF(AND(R34<>"修改",S34<>""),"只有「修改」才需填代碼","")) | AA34: e670fbcc9435d64e497e916b
A35: 34 | B35: 2026-10-06 | C35: ACN | D35: Accenture plc Class A Ordinary Shares (I | E35: FBI removed an Accenture contractor after a data breach exposed thousands of employees' records | G35: Quartz | H35: -0.942 | I35: DATA_BREACH | J35: 資料外洩 | K35: 3 | M35: 維持 | O35: 高 | P35: FBI 因資料外洩與未修補漏洞，終止與 Accenture 承包商合作。 | R35: 維持 | T35: =IF(R35="維持",J35,IF(R35="排除","無關新聞事件",IFERROR(INDEX(事件規則!$B$2:$B$53,MATCH(S35,事件規則!$A$2:$A$53,0)),""))) -> 資料外洩 | U35: =IF(R35="維持",K35,IF(R35="排除",0,IFERROR(INDEX(事件規則!$C$2:$C$53,MATCH(S35,事件規則!$A$2:$A$53,0)),""))) -> 3 | X35: =IF(AND(R35="修改",S35=""),"請選新事件代碼",IF(AND(R35<>"修改",S35<>""),"只有「修改」才需填代碼","")) | AA35: 3c3c6443bddbd1fa0ca616a7
A36: 35 | B36: 2026-10-08 | C36: GS | D36: Goldman Sachs | E36: Goldman Sachs Ensnared in EY Data Breach Earlier This Year | G36: Claims Journal | H36: -0.847 | I36: DATA_BREACH | J36: 資料外洩 | K36: 3 | M36: 維持 | O36: 中 | P36: Goldman Sachs 受 EY 資料外洩牽連（第三方事件）。 | R36: 維持 | T36: =IF(R36="維持",J36,IF(R36="排除","無關新聞事件",IFERROR(INDEX(事件規則!$B$2:$B$53,MATCH(S36,事件規則!$A$2:$A$53,0)),""))) -> 資料外洩 | U36: =IF(R36="維持",K36,IF(R36="排除",0,IFERROR(INDEX(事件規則!$C$2:$C$53,MATCH(S36,事件規則!$A$2:$A$53,0)),""))) -> 3 | X36: =IF(AND(R36="修改",S36=""),"請選新事件代碼",IF(AND(R36<>"修改",S36<>""),"只有「修改」才需填代碼","")) | AA36: 0c48ccb7c65f57c24ba2ac79
A37: 36 | B37: 2026-10-15 | C37: CNP | D37: CenterPoint Energy | E37: 1M Impacted by CenterPoint Energy Data Breach | F37: 100 萬人受到 CenterPoint 能源資料外洩的影響 | G37: Security Magazine | H37: -0.954 | I37: DATA_BREACH | J37: 資料外洩 | K37: 3 | M37: 維持 | O37: 高 | P37: CenterPoint Energy 資料外洩影響逾 100 萬名客戶。 | R37: 維持 | T37: =IF(R37="維持",J37,IF(R37="排除","無關新聞事件",IFERROR(INDEX(事件規則!$B$2:$B$53,MATCH(S37,事件規則!$A$2:$A$53,0)),""))) -> 資料外洩 | U37: =IF(R37="維持",K37,IF(R37="排除",0,IFERROR(INDEX(事件規則!$C$2:$C$53,MATCH(S37,事件規則!$A$2:$A$53,0)),""))) -> 3 | X37: =IF(AND(R37="修改",S37=""),"請選新事件代碼",IF(AND(R37<>"修改",S37<>""),"只有「修改」才需填代碼","")) | AA37: 526c02dc8a51f4dfb3eed28b
A38: 37 | B38: 2026-10-15 | C38: CNP | D38: CenterPoint Energy | E38: More than 1 million customers affected in CenterPoint Energy data breach, Texas DA’s office says | F38: 德州地方檢察官辦公室表示，超過 100 萬名客戶因 CenterPoint Energy 資料外洩而受到影響 | G38: CW39 Houston | H38: -0.919 | I38: DATA_BREACH | J38: 資料外洩 | K38: 3 | M38: 維持 | O38: 高 | P38: CenterPoint Energy 資料外洩影響逾 100 萬名客戶。 | R38: 維持 | T38: =IF(R38="維持",J38,IF(R38="排除","無關新聞事件",IFERROR(INDEX(事件規則!$B$2:$B$53,MATCH(S38,事件規則!$A$2:$A$53,0)),""))) -> 資料外洩 | U38: =IF(R38="維持",K38,IF(R38="排除",0,IFERROR(INDEX(事件規則!$C$2:$C$53,MATCH(S38,事件規則!$A$2:$A$53,0)),""))) -> 3 | X38: =IF(AND(R38="修改",S38=""),"請選新事件代碼",IF(AND(R38<>"修改",S38<>""),"只有「修改」才需填代碼","")) | AA38: a160021d837a200295fca910
A39: 38 | B39: 2026-10-15 | C39: CNP | D39: CenterPoint Energy | E39: CenterPoint Energy Data Breach Impacts 1 Million Texans | F39: CenterPoint 能源資料外洩影響 100 萬德州人 | G39: SecurityWeek | H39: -0.445 | I39: DATA_BREACH | J39: 資料外洩 | K39: 3 | M39: 維持 | O39: 高 | P39: CenterPoint Energy 資料外洩影響逾 100 萬名客戶。 | R39: 維持 | T39: =IF(R39="維持",J39,IF(R39="排除","無關新聞事件",IFERROR(INDEX(事件規則!$B$2:$B$53,MATCH(S39,事件規則!$A$2:$A$53,0)),""))) -> 資料外洩 | U39: =IF(R39="維持",K39,IF(R39="排除",0,IFERROR(INDEX(事件規則!$C$2:$C$53,MATCH(S39,事件規則!$A$2:$A$53,0)),""))) -> 3 | X39: =IF(AND(R39="修改",S39=""),"請選新事件代碼",IF(AND(R39<>"修改",S39<>""),"只有「修改」才需填代碼","")) | AA39: fa26c8a2a64ef24eee780b89
A40: 39 | B40: 2026-10-15 | C40: CNP | D40: CenterPoint Energy | E40: More than 1 million customers impacted by CenterPoint Energy data breach, AG report filing shows | F40: AG 報告顯示，超過 100 萬名客戶受到 CenterPoint Energy 資料外洩的影響 | G40: ABC13 Houston | H40: -0.925 | I40: DATA_BREACH | J40: 資料外洩 | K40: 3 | M40: 維持 | O40: 高 | P40: CenterPoint Energy 資料外洩影響逾 100 萬名客戶。 | R40: 維持 | T40: =IF(R40="維持",J40,IF(R40="排除","無關新聞事件",IFERROR(INDEX(事件規則!$B$2:$B$53,MATCH(S40,事件規則!$A$2:$A$53,0)),""))) -> 資料外洩 | U40: =IF(R40="維持",K40,IF(R40="排除",0,IFERROR(INDEX(事件規則!$C$2:$C$53,MATCH(S40,事件規則!$A$2:$A$53,0)),""))) -> 3 | X40: =IF(AND(R40="修改",S40=""),"請選新事件代碼",IF(AND(R40<>"修改",S40<>""),"只有「修改」才需填代碼","")) | AA40: 28f260be7eac8f93590dbec7
A41: 40 | B41: 2026-08-09 | C41: META | D41: Meta Platforms, Inc. | E41: Cathie Wood's Ark Piled Into Nvidia and Taiwan Semiconductor After Meta's Earnings Miss. Here's What It Signals for Artificial Intelligence (AI) Stocks. | F41: Meta 的獲利未達標後，Cathie Wood 的方舟紛紛買進英偉達和台積電。以下是人工智慧 (AI) 股票的訊號。 | G41: The Motley Fool | H41: 0.01 | I41: EARNINGS_MISS | J41: 財報不如預期 | K41: 3 | M41: 排除 | O41: 中 | P41: Ark 基金交易評論，只提到 Meta 財報不如預期，不是公司事件本身。 | R41: 排除 | T41: =IF(R41="維持",J41,IF(R41="排除","無關新聞事件",IFERROR(INDEX(事件規則!$B$2:$B$53,MATCH(S41,事件規則!$A$2:$A$53,0)),""))) -> 無關新聞事件 | U41: =IF(R41="維持",K41,IF(R41="排除",0,IFERROR(INDEX(事件規則!$C$2:$C$53,MATCH(S41,事件規則!$A$2:$A$53,0)),""))) -> 0 | X41: =IF(AND(R41="修改",S41=""),"請選新事件代碼",IF(AND(R41<>"修改",S41<>""),"只有「修改」才需填代碼","")) | AA41: 705eabf69f239b628c12d34f
A42: 41 | B42: 2026-08-09 | C42: NVDA | D42: NVIDIA Corporation | E42: Cathie Wood's Ark Piled Into Nvidia and Taiwan Semiconductor After Meta's Earnings Miss. Here's What It Signals for Artificial Intelligence (AI) Stocks. | F42: Meta 的獲利未達標後，Cathie Wood 的方舟紛紛買進英偉達和台積電。以下是人工智慧 (AI) 股票的訊號。 | G42: Yahoo Finance | H42: 0.01 | I42: EARNINGS_MISS | J42: 財報不如預期 | K42: 3 | M42: 排除 | O42: 中 | P42: Ark 基金交易評論，只提到 Meta 財報不如預期，不是公司事件本身。 | R42: 排除 | T42: =IF(R42="維持",J42,IF(R42="排除","無關新聞事件",IFERROR(INDEX(事件規則!$B$2:$B$53,MATCH(S42,事件規則!$A$2:$A$53,0)),""))) -> 無關新聞事件 | U42: =IF(R42="維持",K42,IF(R42="排除",0,IFERROR(INDEX(事件規則!$C$2:$C$53,MATCH(S42,事件規則!$A$2:$A$53,0)),""))) -> 0 | X42: =IF(AND(R42="修改",S42=""),"請選新事件代碼",IF(AND(R42<>"修改",S42<>""),"只有「修改」才需填代碼","")) | AA42: 280826a9a8d021b3b0a3a85c
A43: 42 | B43: 2026-08-10 | C43: DRI | D43: Darden Restaurants, Inc. Common Stock | E43: Earnings call transcript: DRI Healthcare Trust posts record Q2 2026 results despite EPS miss | F43: 財報電話會議記錄：儘管 EPS 未達預期，DRI 醫療保健信託仍公佈 2026 年第二季創紀錄業績 | G43: Investing.com | H43: 0.868 | I43: EARNINGS_MISS | J43: 財報不如預期 | K43: 3 | M43: 排除 | O43: 高 | P43: DRI Healthcare Trust 與 Darden 無關（公司誤配）。 | R43: 排除 | T43: =IF(R43="維持",J43,IF(R43="排除","無關新聞事件",IFERROR(INDEX(事件規則!$B$2:$B$53,MATCH(S43,事件規則!$A$2:$A$53,0)),""))) -> 無關新聞事件 | U43: =IF(R43="維持",K43,IF(R43="排除",0,IFERROR(INDEX(事件規則!$C$2:$C$53,MATCH(S43,事件規則!$A$2:$A$53,0)),""))) -> 0 | X43: =IF(AND(R43="修改",S43=""),"請選新事件代碼",IF(AND(R43<>"修改",S43<>""),"只有「修改」才需填代碼","")) | AA43: 67ddb0f5f237ddb8c67fcffd
A44: 43 | B44: 2026-08-10 | C44: TKO | D44: TKO Group Holdings, Inc. Class A Common | E44: Taseko Mines Ltd TKO Earnings Miss Estimates by 8.3% | F44: Taseko Mines Ltd TKO 獲利比預期低 8.3% | G44: Wealth Awesome | H44: -0.955 | I44: EARNINGS_MISS | J44: 財報不如預期 | K44: 3 | M44: 排除 | O44: 高 | P44: Taseko Mines 與 TKO 無關（公司誤配）。 | R44: 排除 | T44: =IF(R44="維持",J44,IF(R44="排除","無關新聞事件",IFERROR(INDEX(事件規則!$B$2:$B$53,MATCH(S44,事件規則!$A$2:$A$53,0)),""))) -> 無關新聞事件 | U44: =IF(R44="維持",K44,IF(R44="排除",0,IFERROR(INDEX(事件規則!$C$2:$C$53,MATCH(S44,事件規則!$A$2:$A$53,0)),""))) -> 0 | X44: =IF(AND(R44="修改",S44=""),"請選新事件代碼",IF(AND(R44<>"修改",S44<>""),"只有「修改」才需填代碼","")) | AA44: 9180002e6f5b989445a148b4
A45: 44 | B45: 2026-08-10 | C45: DRI | D45: Darden Restaurants, Inc. Common Stock | E45: DRI Healthcare Trust DHT-UN Earnings Miss Estimates by 6.7% | F45: DRI 醫療保健信託基金 DHT-UN 獲利比預期低 6.7% | G45: Wealth Awesome | H45: -0.94 | I45: EARNINGS_MISS | J45: 財報不如預期 | K45: 3 | M45: 排除 | O45: 高 | P45: DRI Healthcare Trust 與 Darden 無關（公司誤配）。 | R45: 排除 | T45: =IF(R45="維持",J45,IF(R45="排除","無關新聞事件",IFERROR(INDEX(事件規則!$B$2:$B$53,MATCH(S45,事件規則!$A$2:$A$53,0)),""))) -> 無關新聞事件 | U45: =IF(R45="維持",K45,IF(R45="排除",0,IFERROR(INDEX(事件規則!$C$2:$C$53,MATCH(S45,事件規則!$A$2:$A$53,0)),""))) -> 0 | X45: =IF(AND(R45="修改",S45=""),"請選新事件代碼",IF(AND(R45<>"修改",S45<>""),"只有「修改」才需填代碼","")) | AA45: f5de0fb43bfb05f0ce34f1bf
A46: 45 | B46: 2026-08-10 | C46: DRI | D46: Darden Restaurants, Inc. Common Stock | E46: DRI Healthcare Trust DHT-U Earnings Miss Estimates by 81.7% | F46: DRI 醫療保健信託基金 DHT-U 獲利比預期低 81.7% | G46: Wealth Awesome | H46: -0.915 | I46: EARNINGS_MISS | J46: 財報不如預期 | K46: 3 | M46: 排除 | O46: 高 | P46: DRI Healthcare Trust 與 Darden 無關（公司誤配）。 | R46: 排除 | T46: =IF(R46="維持",J46,IF(R46="排除","無關新聞事件",IFERROR(INDEX(事件規則!$B$2:$B$53,MATCH(S46,事件規則!$A$2:$A$53,0)),""))) -> 無關新聞事件 | U46: =IF(R46="維持",K46,IF(R46="排除",0,IFERROR(INDEX(事件規則!$C$2:$C$53,MATCH(S46,事件規則!$A$2:$A$53,0)),""))) -> 0 | X46: =IF(AND(R46="修改",S46=""),"請選新事件代碼",IF(AND(R46<>"修改",S46<>""),"只有「修改」才需填代碼","")) | AA46: 41eb27f3a18a6fc6608d1bb7
A47: 46 | B47: 2026-08-10 | C47: PNC | D47: PNC Financial Services | E47: Earnings call transcript: PNC Infratech Q1 2027 profit miss sparks 6.3% drop | F47: 財報電話會議紀錄：PNC Infratech 2027 年第一季獲利未達標導致下降 6.3% | G47: Investing.com | H47: -0.711 | I47: EARNINGS_MISS | J47: 財報不如預期 | K47: 3 | M47: 排除 | O47: 高 | P47: PNC Infratech 與 PNC Financial 無關（公司誤配）。 | R47: 排除 | T47: =IF(R47="維持",J47,IF(R47="排除","無關新聞事件",IFERROR(INDEX(事件規則!$B$2:$B$53,MATCH(S47,事件規則!$A$2:$A$53,0)),""))) -> 無關新聞事件 | U47: =IF(R47="維持",K47,IF(R47="排除",0,IFERROR(INDEX(事件規則!$C$2:$C$53,MATCH(S47,事件規則!$A$2:$A$53,0)),""))) -> 0 | X47: =IF(AND(R47="修改",S47=""),"請選新事件代碼",IF(AND(R47<>"修改",S47<>""),"只有「修改」才需填代碼","")) | AA47: d1b2fe254dbd40c0fe61ddea
A48: 47 | B48: 2026-08-10 | C48: EA | D48: Electronic Arts | E48: Electronic Arts Stock Exits Nasdaq at $209.70 as Deal Mechanics Eclipse Earnings Miss | F48: 藝電股票以 209.70 美元退出納斯達克，交易機制讓獲利黯然失色 | G48: TechStock² | H48: -0.859 | I48: EARNINGS_MISS | J48: 財報不如預期 | K48: 3 | M48: 排除 | O48: 中 | P48: EA 完成私有化下市，財報不如預期已不重要。 | R48: 排除 | T48: =IF(R48="維持",J48,IF(R48="排除","無關新聞事件",IFERROR(INDEX(事件規則!$B$2:$B$53,MATCH(S48,事件規則!$A$2:$A$53,0)),""))) -> 無關新聞事件 | U48: =IF(R48="維持",K48,IF(R48="排除",0,IFERROR(INDEX(事件規則!$C$2:$C$53,MATCH(S48,事件規則!$A$2:$A$53,0)),""))) -> 0 | X48: =IF(AND(R48="修改",S48=""),"請選新事件代碼",IF(AND(R48<>"修改",S48<>""),"只有「修改」才需填代碼","")) | AA48: bde2eb909d061bb6427dee53
... A56: 55 | B56: 2026-08-15 | C56: TTD | D56: Trade Desk (The) | E56: TTD Stock Sinks Over 26% On Earnings Miss, Weak Outlook — Retail Says Trade Desk’s Guidance Is The Real Problem | F56: TTD 股價因盈利不佳和前景疲軟而下跌超過 26% — 零售業表示 Trade Desk 的指導才是真正的問題 | G56: Stocktwits | H56: -0.957 | I56: EARNINGS_MISS | J56: 財報不如預期 | K56: 3 | M56: 維持 | O56: 高 | P56: Trade Desk 財報不如預期、展望疲弱，股價重挫逾 26%。 | R56: 維持 | T56: =IF(R56="維持",J56,IF(R56="排除","無關新聞事件",IFERROR(INDEX(事件規則!$B$2:$B$53,MATCH(S56,事件規則!$A$2:$A$53,0)),""))) -> 財報不如預期 | U56: =IF(R56="維持",K56,IF(R56="排除",0,IFERROR(INDEX(事件規則!$C$2:$C$53,MATCH(S56,事件規則!$A$2:$A$53,0)),""))) -> 3 | X56: =IF(AND(R56="修改",S56=""),"請選新事件代碼",IF(AND(R56<>"修改",S56<>""),"只有「修改」才需填代碼","")) | AA56: 9d95623c9dd011b866d26579
A57: 56 | B57: 2026-08-19 | C57: ES | D57: Eversource Energy | E57: Eversource (ES) Financial Update: EPS Misses Its Estimate under the Current Snapshot; Session Reaction: The Stock Ends Up 0.43% at the Close - Quarterly Earnings Report | G57: vinanet.vn | H57: 0.322 | I57: EARNINGS_MISS | J57: 財報不如預期 | K57: 3 | M57: 排除 | O57: 中 | P57: Eversource EPS 小幅低於預期，市場反應不明顯。 | R57: 排除 | T57: =IF(R57="維持",J57,IF(R57="排除","無關新聞事件",IFERROR(INDEX(事件規則!$B$2:$B$53,MATCH(S57,事件規則!$A$2:$A$53,0)),""))) -> 無關新聞事件 | U57: =IF(R57="維持",K57,IF(R57="排除",0,IFERROR(INDEX(事件規則!$C$2:$C$53,MATCH(S57,事件規則!$A$2:$A$53,0)),""))) -> 0 | X57: =IF(AND(R57="修改",S57=""),"請選新事件代碼",IF(AND(R57<>"修改",S57<>""),"只有「修改」才需填代碼","")) | AA57: 0f01c7d4a0fd1ba5bfe6dd13
A58: 57 | B58: 2026-08-20 | C58: DOW | D58: Dow Inc. Common Stock | E58: Dow drops 600 points on rising yields, Walmart earnings miss | G58: finance.yahoo.com | H58: -0.867 | I58: EARNINGS_MISS | J58: 財報不如預期 | K58: 3 | M58: 排除 | O58: 高 | P58: 道瓊指數下跌新聞，Dow 指 Dow Jones 而非 Dow Inc.，且是 Walmart 財報。 | R58: 排除 | T58: =IF(R58="維持",J58,IF(R58="排除","無關新聞事件",IFERROR(INDEX(事件規則!$B$2:$B$53,MATCH(S58,事件規則!$A$2:$A$53,0)),""))) -> 無關新聞事件 | U58: =IF(R58="維持",K58,IF(R58="排除",0,IFERROR(INDEX(事件規則!$C$2:$C$53,MATCH(S58,事件規則!$A$2:$A$53,0)),""))) -> 0 | X58: =IF(AND(R58="修改",S58=""),"請選新事件代碼",IF(AND(R58<>"修改",S58<>""),"只有「修改」才需填代碼","")) | AA58: cd9e7fa383a3406940cf5220
A59: 58 | B59: 2026-08-20 | C59: AZO | D59: AutoZone, Inc. Common Stock | E59: Advance Auto Parts Plunges 21% as Revenue Miss Overshadows Earnings Beat; AutoZone Falls 4%, O'Reilly Automotive Slips | G59: 24/7 Wall St. | H59: -0.948 | I59: EARNINGS_MISS | J59: 財報不如預期 | K59: 3 | M59: 排除 | O59: 中 | P59: 主角是 Advance Auto Parts 重挫，AutoZone 只小跌 4%。 | R59: 排除 | T59: =IF(R59="維持",J59,IF(R59="排除","無關新聞事件",IFERROR(INDEX(事件規則!$B$2:$B$53,MATCH(S59,事件規則!$A$2:$A$53,0)),""))) -> 無關新聞事件 | U59: =IF(R59="維持",K59,IF(R59="排除",0,IFERROR(INDEX(事件規則!$C$2:$C$53,MATCH(S59,事件規則!$A$2:$A$53,0)),""))) -> 0 | X59: =IF(AND(R59="修改",S59=""),"請選新事件代碼",IF(AND(R59<>"修改",S59<>""),"只有「修改」才需填代碼","")) | AA59: 908d5cfc2f0f8f14818d4cd3
A60: 59 | B60: 2026-08-25 | C60: COIN | D60: Coinbase | E60: COIN Stock Slides After Earnings Miss — Coinbase CEO Says The Crypto Exchange Is Becoming More Than A Bitcoin Bet | G60: Stocktwits | H60: -0.94 | I60: EARNINGS_MISS | J60: 財報不如預期 | K60: 3 | M60: 維持 | O60: 中 | P60: Coinbase 財報不如預期，股價下滑。 | R60: 維持 | T60: =IF(R60="維持",J60,IF(R60="排除","無關新聞事件",IFERROR(INDEX(事件規則!$B$2:$B$53,MATCH(S60,事件規則!$A$2:$A$53,0)),""))) -> 財報不如預期 | U60: =IF(R60="維持",K60,IF(R60="排除",0,IFERROR(INDEX(事件規則!$C$2:$C$53,MATCH(S60,事件規則!$A$2:$A$53,0)),""))) -> 3 | X60: =IF(AND(R60="修改",S60=""),"請選新事件代碼",IF(AND(R60<>"修改",S60<>""),"只有「修改」才需填代碼","")) | AA60: 5a7609b07982daf1e9fe7d5d
A61: 60 | B61: 2026-09-04 | C61: LULU | D61: lululemon athletica inc. | E61: LULU: Revenue and earnings missed expectations, prompting lower guidance and renewed focus on innovation | F61: LULU：收入和利潤未達預期，導致指引下調並重新專注於創新 | G61: TradingView | H61: -0.935 | I61: EARNINGS_MISS | J61: 財報不如預期 | K61: 3 | M61: 維持 | O61: 高 | P61: lululemon 營收與獲利未達預期並下調展望，股價跌 15%。 | R61: 維持 | T61: =IF(R61="維持",J61,IF(R61="排除","無關新聞事件",IFERROR(INDEX(事件規則!$B$2:$B$53,MATCH(S61,事件規則!$A$2:$A$53,0)),""))) -> 財報不如預期 | U61: =IF(R61="維持",K61,IF(R61="排除",0,IFERROR(INDEX(事件規則!$C$2:$C$53,MATCH(S61,事件規則!$A$2:$A$53,0)),""))) -> 3 | X61: =IF(AND(R61="修改",S61=""),"請選新事件代碼",IF(AND(R61<>"修改",S61<>""),"只有「修改」才需填代碼","")) | AA61: d13f5f3fd0d9e26de9f10867
A62: 61 | B62: 2026-09-04 | C62: LULU | D62: lululemon athletica inc. | E62: Lululemon (NASDAQ:LULU) Tumbles 15% on Revenue Miss and Weak Guidance | F62: Lululemon（納斯達克股票代碼：LULU）因收入失誤和指引疲軟而下跌 15% | G62: ChartMill | H62: -0.966 | I62: EARNINGS_MISS | J62: 財報不如預期 | K62: 3 | M62: 維持 | O62: 高 | P62: lululemon 營收與獲利未達預期並下調展望，股價跌 15%。 | R62: 維持 | T62: =IF(R62="維持",J62,IF(R62="排除","無關新聞事件",IFERROR(INDEX(事件規則!$B$2:$B$53,MATCH(S62,事件規則!$A$2:$A$53,0)),""))) -> 財報不如預期 | U62: =IF(R62="維持",K62,IF(R62="排除",0,IFERROR(INDEX(事件規則!$C$2:$C$53,MATCH(S62,事件規則!$A$2:$A$53,0)),""))) -> 3 | X62: =IF(AND(R62="修改",S62=""),"請選新事件代碼",IF(AND(R62<>"修改",S62<>""),"只有「修改」才需填代碼","")) | AA62: 62a05513f80266032cd6843e
A63: 62 | B63: 2026-09-10 | C63: CPRT | D63: Copart, Inc. | E63: Copart (NASDAQ:CPRT) Stock Surges After Hours on Reported ACV Acquisition Despite Q4 EPS Miss | G63: ChartMill | H63: 0.61 | I63: EARNINGS_MISS | J63: 財報不如預期 | K63: 3 | M63: 排除 | O63: 中 | P63: 財報好壞參半（EPS 或營收其中之一未達預期），股價未顯著受壓。 | R63: 排除 | T63: =IF(R63="維持",J63,IF(R63="排除","無關新聞事件",IFERROR(INDEX(事件規則!$B$2:$B$53,MATCH(S63,事件規則!$A$2:$A$53,0)),""))) -> 無關新聞事件 | U63: =IF(R63="維持",K63,IF(R63="排除",0,IFERROR(INDEX(事件規則!$C$2:$C$53,MATCH(S63,事件規則!$A$2:$A$53,0)),""))) -> 0 | X63: =IF(AND(R63="修改",S63=""),"請選新事件代碼",IF(AND(R63<>"修改",S63<>""),"只有「修改」才需填代碼","")) | AA63: 5e973c886a6dc88dee4aeaaa
A64: 63 | B64: 2026-09-16 | C64: LEN | D64: Lennar Corporation Class A Common Stock | E64: Lennar Q3 earnings miss; guidance disappoints (LEN:NYSE) | G64: Seeking Alpha | H64: -0.953 | I64: EARNINGS_MISS | J64: 財報不如預期 | K64: 3 | M64: 維持 | O64: 高 | P64: Lennar 第三季財報不如預期且展望令人失望。 | R64: 維持 | T64: =IF(R64="維持",J64,IF(R64="排除","無關新聞事件",IFERROR(INDEX(事件規則!$B$2:$B$53,MATCH(S64,事件規則!$A$2:$A$53,0)),""))) -> 財報不如預期 | U64: =IF(R64="維持",K64,IF(R64="排除",0,IFERROR(INDEX(事件規則!$C$2:$C$53,MATCH(S64,事件規則!$A$2:$A$53,0)),""))) -> 3 | X64: =IF(AND(R64="修改",S64=""),"請選新事件代碼",IF(AND(R64<>"修改",S64<>""),"只有「修改」才需填代碼","")) | AA64: 8cda12a45d54c01a2b61101c
A65: 64 | B65: 2026-09-17 | C65: LEN | D65: Lennar Corporation Class A Common Stock | E65: Lennar Q3 Earnings Miss Estimates on Housing Weakness, Revenues Lag | G65: Yahoo Finance | H65: -0.955 | I65: EARNINGS_MISS | J65: 財報不如預期 | K65: 3 | M65: 維持 | O65: 高 | P65: Lennar 第三季財報不如預期且展望令人失望。 | R65: 維持 | T65: =IF(R65="維持",J65,IF(R65="排除","無關新聞事件",IFERROR(INDEX(事件規則!$B$2:$B$53,MATCH(S65,事件規則!$A$2:$A$53,0)),""))) -> 財報不如預期 | U65: =IF(R65="維持",K65,IF(R65="排除",0,IFERROR(INDEX(事件規則!$C$2:$C$53,MATCH(S65,事件規則!$A$2:$A$53,0)),""))) -> 3 | X65: =IF(AND(R65="修改",S65=""),"請選新事件代碼",IF(AND(R65<>"修改",S65<>""),"只有「修改」才需填代碼","")) | AA65: 643c78860fe605f4befdf93b
A66: 65 | B66: 2026-09-19 | C66: LEN | D66: Lennar Corporation Class A Common Stock | E66: Lennar’s Earnings Miss May Be Sending a Bigger Warning About U.S. Housing | G66: Yahoo Finance | H66: -0.921 | I66: EARNINGS_MISS | J66: 財報不如預期 | K66: 3 | M66: 維持 | O66: 中 | P66: Lennar 財報不如預期，被視為美國房市的警訊。 | R66: 維持 | T66: =IF(R66="維持",J66,IF(R66="排除","無關新聞事件",IFERROR(INDEX(事件規則!$B$2:$B$53,MATCH(S66,事件規則!$A$2:$A$53,0)),""))) -> 財報不如預期 | U66: =IF(R66="維持",K66,IF(R66="排除",0,IFERROR(INDEX(事件規則!$C$2:$C$53,MATCH(S66,事件規則!$A$2:$A$53,0)),""))) -> 3 | X66: =IF(AND(R66="修改",S66=""),"請選新事件代碼",IF(AND(R66<>"修改",S66<>""),"只有「修改」才需填代碼","")) | AA66: 35c2f650041aceb96195e59f
A67: 66 | B67: 2026-09-22 | C67: AZO | D67: AutoZone, Inc. Common Stock | E67: AutoZone Climbs 6% as Profit Beat Offsets Revenue Miss; Advance Auto Parts Rises 6%, O'Reilly Automotive Gains 4% | G67: 24/7 Wall St. | H67: 0.895 | I67: EARNINGS_MISS | J67: 財報不如預期 | K67: 3 | M67: 排除 | O67: 高 | P67: 獲利優於預期（只有營收略低），屬正面或中性結果。 | R67: 排除 | T67: =IF(R67="維持",J67,IF(R67="排除","無關新聞事件",IFERROR(INDEX(事件規則!$B$2:$B$53,MATCH(S67,事件規則!$A$2:$A$53,0)),""))) -> 無關新聞事件 | U67: =IF(R67="維持",K67,IF(R67="排除",0,IFERROR(INDEX(事件規則!$C$2:$C$53,MATCH(S67,事件規則!$A$2:$A$53,0)),""))) -> 0 | X67: =IF(AND(R67="修改",S67=""),"請選新事件代碼",IF(AND(R67<>"修改",S67<>""),"只有「修改」才需填代碼","")) | AA67: 1a0377ef33f45dfd169e6928
A68: 67 | B68: 2026-09-28 | C68: EXC | D68: Exelon Corporation | E68: Exelon stock faces lower targets after Q2 earnings miss | G68: ad-hoc-news.de | H68: -0.831 | I68: EARNINGS_MISS | J68: 財報不如預期 | K68: 3 | M68: 排除 | O68: 中 | P68: 估值或目標價評論，不是財報事件本身。 | R68: 排除 | T68: =IF(R68="維持",J68,IF(R68="排除","無關新聞事件",IFERROR(INDEX(事件規則!$B$2:$B$53,MATCH(S68,事件規則!$A$2:$A$53,0)),""))) -> 無關新聞事件 | U68: =IF(R68="維持",K68,IF(R68="排除",0,IFERROR(INDEX(事件規則!$C$2:$C$53,MATCH(S68,事件規則!$A$2:$A$53,0)),""))) -> 0 | X68: =IF(AND(R68="修改",S68=""),"請選新事件代碼",IF(AND(R68<>"修改",S68<>""),"只有「修改」才需填代碼","")) | AA68: 30b53c78b9a25a4a3af002ef
A69: 68 | B69: 2026-09-28 | C69: DRI | D69: Darden Restaurants, Inc. Common Stock | E69: Darden Restaurants (DRI) Stock May Be 13% Undervalued After Q1 Earnings Miss | G69: Yahoo Finance | H69: -0.824 | I69: EARNINGS_MISS | J69: 財報不如預期 | K69: 3 | M69: 排除 | O69: 中 | P69: 估值或目標價評論，不是財報事件本身。 | R69: 排除 | T69: =IF(R69="維持",J69,IF(R69="排除","無關新聞事件",IFERROR(INDEX(事件規則!$B$2:$B$53,MATCH(S69,事件規則!$A$2:$A$53,0)),""))) -> 無關新聞事件 | U69: =IF(R69="維持",K69,IF(R69="排除",0,IFERROR(INDEX(事件規則!$C$2:$C$53,MATCH(S69,事件規則!$A$2:$A$53,0)),""))) -> 0 | X69: =IF(AND(R69="修改",S69=""),"請選新事件代碼",IF(AND(R69<>"修改",S69<>""),"只有「修改」才需填代碼","")) | AA69: 260bef3068ad46f360e48c7b
A70: 69 | B70: 2026-10-09 | C70: DAL | D70: Delta Air Lines, Inc. Common Stock | E70: DAL Q3 Earnings Miss Estimates as Higher Fuel Costs Hurt Margins | G70: Yahoo Finance | H70: -0.951 | I70: EARNINGS_MISS | J70: 財報不如預期 | K70: 3 | M70: 維持 | O70: 中 | P70: Delta 第三季財報不如預期，燃料成本侵蝕利潤。 | R70: 維持 | T70: =IF(R70="維持",J70,IF(R70="排除","無關新聞事件",IFERROR(INDEX(事件規則!$B$2:$B$53,MATCH(S70,事件規則!$A$2:$A$53,0)),""))) -> 財報不如預期 | U70: =IF(R70="維持",K70,IF(R70="排除",0,IFERROR(INDEX(事件規則!$C$2:$C$53,MATCH(S70,事件規則!$A$2:$A$53,0)),""))) -> 3 | X70: =IF(AND(R70="修改",S70=""),"請選新事件代碼",IF(AND(R70<>"修改",S70<>""),"只有「修改」才需填代碼","")) | AA70: 7d63275fbd7f3da8f5877808
A71: 70 | B71: 2026-10-09 | C71: DAL | D71: Delta Air Lines, Inc. Common Stock | E71: Delta Air Lines Shares Fall as Third-Quarter Earnings Miss Forecasts and Full-Year Outlook Is Cut | G71: Yahoo Finance | H71: -0.964 | I71: EARNINGS_MISS | J71: 財報不如預期 | K71: 3 | M71: 維持 | O71: 高 | P71: Delta 第三季不如預期並下調全年展望，股價下跌。 | R71: 維持 | T71: =IF(R71="維持",J71,IF(R71="排除","無關新聞事件",IFERROR(INDEX(事件規則!$B$2:$B$53,MATCH(S71,事件規則!$A$2:$A$53,0)),""))) -> 財報不如預期 | U71: =IF(R71="維持",K71,IF(R71="排除",0,IFERROR(INDEX(事件規則!$C$2:$C$53,MATCH(S71,事件規則!$A$2:$A$53,0)),""))) -> 3 | X71: =IF(AND(R71="修改",S71=""),"請選新事件代碼",IF(AND(R71<>"修改",S71<>""),"只有「修改」才需填代碼","")) | AA71: 65abd5e282d9ab8570074472
A72: 71 | B72: 2026-10-15 | C72: PNC | D72: PNC Financial Services | E72: PNC Q3 2026 earnings show revenue of $6.56 billion missed estimates | F72: PNC 2026 年第三季財報顯示，營收達 65.6 億美元，未達預期 | G72: Quartz | H72: 0.02 | I72: EARNINGS_MISS | J72: 財報不如預期 | K72: 3 | M72: 排除 | O72: 中 | P72: 財報好壞參半（EPS 或營收其中之一未達預期），股價未顯著受壓。 | R72: 排除 | T72: =IF(R72="維持",J72,IF(R72="排除","無關新聞事件",IFERROR(INDEX(事件規則!$B$2:$B$53,MATCH(S72,事件規則!$A$2:$A$53,0)),""))) -> 無關新聞事件 | U72: =IF(R72="維持",K72,IF(R72="排除",0,IFERROR(INDEX(事件規則!$C$2:$C$53,MATCH(S72,事件規則!$A$2:$A$53,0)),""))) -> 0 | X72: =IF(AND(R72="修改",S72=""),"請選新事件代碼",IF(AND(R72<>"修改",S72<>""),"只有「修改」才需填代碼","")) | AA72: e364fbee8424570f44cea339
A73: 72 | B73: 2026-10-15 | C73: USB | D73: U.S. Bancorp Common Stock | E73: U.S. Bancorp beats earnings despite revenue miss | F73: 儘管收入低於預期，美國合眾銀行仍實現獲利 | G73: Yahoo Finance | H73: 0.085 | I73: EARNINGS_MISS | J73: 財報不如預期 | K73: 3 | M73: 排除 | O73: 高 | P73: 獲利優於預期（只有營收略低），屬正面或中性結果。 | R73: 排除 | T73: =IF(R73="維持",J73,IF(R73="排除","無關新聞事件",IFERROR(INDEX(事件規則!$B$2:$B$53,MATCH(S73,事件規則!$A$2:$A$53,0)),""))) -> 無關新聞事件 | U73: =IF(R73="維持",K73,IF(R73="排除",0,IFERROR(INDEX(事件規則!$C$2:$C$53,MATCH(S73,事件規則!$A$2:$A$53,0)),""))) -> 0 | X73: =IF(AND(R73="修改",S73=""),"請選新事件代碼",IF(AND(R73<>"修改",S73<>""),"只有「修改」才需填代碼","")) | AA73: e4f16d41248b04632e676f70
A74: 73 | B74: 2026-10-15 | C74: USB | D74: U.S. Bancorp Common Stock | E74: U.S. Bancorp Q3 earnings beat, as expense control offsets revenue miss (USB:NYSE) | F74: 美國合眾銀行第三季獲利超出預期，費用控制抵消了收入損失（USB：NYSE） | G74: Seeking Alpha | H74: 0.806 | I74: EARNINGS_MISS | J74: 財報不如預期 | K74: 3 | M74: 排除 | O74: 高 | P74: 獲利優於預期（只有營收略低），屬正面或中性結果。 | R74: 排除 | T74: =IF(R74="維持",J74,IF(R74="排除","無關新聞事件",IFERROR(INDEX(事件規則!$B$2:$B$53,MATCH(S74,事件規則!$A$2:$A$53,0)),""))) -> 無關新聞事件 | U74: =IF(R74="維持",K74,IF(R74="排除",0,IFERROR(INDEX(事件規則!$C$2:$C$53,MATCH(S74,事件規則!$A$2:$A$53,0)),""))) -> 0 | X74: =IF(AND(R74="修改",S74=""),"請選新事件代碼",IF(AND(R74<>"修改",S74<>""),"只有「修改」才需填代碼","")) | AA74: 59e53b066d7c104e860fd7d9
A75: 74 | B75: 2026-10-15 | C75: PNC | D75: PNC Financial Services | E75: PNC Third-Quarter Lending Revenue Misses Estimates as Costs Beat | F75: 由於成本超出預期，PNC 第三季貸款收入未達預期 | G75: Yahoo Finance | H75: -0.939 | I75: EARNINGS_MISS | J75: 財報不如預期 | K75: 3 | M75: 排除 | O75: 中 | P75: 財報好壞參半（EPS 或營收其中之一未達預期），股價未顯著受壓。 | R75: 排除 | T75: =IF(R75="維持",J75,IF(R75="排除","無關新聞事件",IFERROR(INDEX(事件規則!$B$2:$B$53,MATCH(S75,事件規則!$A$2:$A$53,0)),""))) -> 無關新聞事件 | U75: =IF(R75="維持",K75,IF(R75="排除",0,IFERROR(INDEX(事件規則!$C$2:$C$53,MATCH(S75,事件規則!$A$2:$A$53,0)),""))) -> 0 | X75: =IF(AND(R75="修改",S75=""),"請選新事件代碼",IF(AND(R75<>"修改",S75<>""),"只有「修改」才需填代碼","")) | AA75: 6b258e858c09ce977170351c
A76: 75 | B76: 2026-10-16 | C76: PNC | D76: PNC Financial Services | E76: PNC Financial Q3 Earnings Beat Estimates on Higher NII, Revenue Miss | F76: PNC Financial 第三季獲利超出預期，因 NII 較高，營收未達預期 | G76: Zacks Investment Research | H76: 0.899 | I76: EARNINGS_MISS | J76: 財報不如預期 | K76: 3 | M76: 排除 | O76: 高 | P76: 獲利優於預期（只有營收略低），屬正面或中性結果。 | R76: 排除 | T76: =IF(R76="維持",J76,IF(R76="排除","無關新聞事件",IFERROR(INDEX(事件規則!$B$2:$B$53,MATCH(S76,事件規則!$A$2:$A$53,0)),""))) -> 無關新聞事件 | U76: =IF(R76="維持",K76,IF(R76="排除",0,IFERROR(INDEX(事件規則!$C$2:$C$53,MATCH(S76,事件規則!$A$2:$A$53,0)),""))) -> 0 | X76: =IF(AND(R76="修改",S76=""),"請選新事件代碼",IF(AND(R76<>"修改",S76<>""),"只有「修改」才需填代碼","")) | AA76: 2587e39ff2aa09c9878f3293
A77: 76 | B77: 2026-10-16 | C77: PNC | D77: PNC Financial Services | E77: PNC posts strong Q3 EPS of $5.09, beating estimates despite slight revenue miss. | F77: PNC 第三季每股收益強勁，達到 5.09 美元，儘管收入略有下降，但仍超出預期。 | G77: Pluang | H77: 0.915 | I77: EARNINGS_MISS | J77: 財報不如預期 | K77: 3 | M77: 排除 | O77: 高 | P77: 獲利優於預期（只有營收略低），屬正面或中性結果。 | R77: 排除 | T77: =IF(R77="維持",J77,IF(R77="排除","無關新聞事件",IFERROR(INDEX(事件規則!$B$2:$B$53,MATCH(S77,事件規則!$A$2:$A$53,0)),""))) -> 無關新聞事件 | U77: =IF(R77="維持",K77,IF(R77="排除",0,IFERROR(INDEX(事件規則!$C$2:$C$53,MATCH(S77,事件規則!$A$2:$A$53,0)),""))) -> 0 | X77: =IF(AND(R77="修改",S77=""),"請選新事件代碼",IF(AND(R77<>"修改",S77<>""),"只有「修改」才需填代碼","")) | AA77: d7a7e70cfcdca5486b0593a1
A78: 77 | B78: 2026-10-22 | C78: PHM | D78: PulteGroup, Inc. Common Stock | E78: PulteGroup stock dips as Q3 earnings miss estimates amid pressure on homebuying demand (PHM:NYSE) | F78: 普爾特集團因第三季財報未達預期，股價下跌，顯示市場對住宅需求的擔憂。 | G78: Seeking Alpha | I78: EARNINGS_MISS | J78: 財報不如預期 | K78: 3 | L78: 已分類 | M78: 維持 | O78: 中 | P78: PulteGroup 第三季財報不如預期，反映購屋需求疲弱。 | R78: 維持 | T78: =IF(R78="維持",J78,IF(R78="排除","無關新聞事件",IFERROR(INDEX(事件規則!$B$2:$B$53,MATCH(S78,事件規則!$A$2:$A$53,0)),""))) -> 財報不如預期 | U78: =IF(R78="維持",K78,IF(R78="排除",0,IFERROR(INDEX(事件規則!$C$2:$C$53,MATCH(S78,事件規則!$A$2:$A$53,0)),""))) -> 3 | X78: =IF(AND(R78="修改",S78=""),"請選新事件代碼",IF(AND(R78<>"修改",S78<>""),"只有「修改」才需填代碼","")) | AA78: a2ffa540ad4cc1c9e2785913
A79: 78 | B79: 2026-08-10 | C79: ZTS | D79: Zoetis Inc. Class A Common Stock | E79: Zoetis Faces Wall Street Reckoning as Guidance Cut Triggers Wave of Downgrades | F79: 碩騰面臨華爾街清算，指引下調引發評等下調浪潮 | G79: AD HOC NEWS | H79: -0.876 | I79: EARNINGS_WARNING | J79: 財測下修 | K79: 3 | M79: 維持 | O79: 高 | P79: Zoetis 下修財測引發多家券商降評。 | R79: 維持 | T79: =IF(R79="維持",J79,IF(R79="排除","無關新聞事件",IFERROR(INDEX(事件規則!$B$2:$B$53,MATCH(S79,事件規則!$A$2:$A$53,0)),""))) -> 財測下修 | U79: =IF(R79="維持",K79,IF(R79="排除",0,IFERROR(INDEX(事件規則!$C$2:$C$53,MATCH(S79,事件規則!$A$2:$A$53,0)),""))) -> 3 | X79: =IF(AND(R79="修改",S79=""),"請選新事件代碼",IF(AND(R79<>"修改",S79<>""),"只有「修改」才需填代碼","")) | AA79: 177560a23db1b9df26b0583a
A80: 79 | B80: 2026-08-10 | C80: TTD | D80: Trade Desk (The) | E80: The Trade Desk Stock (TTD) Opinions on Earnings Miss and Guidance Cut | F80: The Trade Desk Stock (TTD) 對獲利未達標和指引下調的看法 | G80: Quiver Quantitative | H80: -0.105 | I80: EARNINGS_WARNING | J80: 財測下修 | K80: 3 | M80: 維持 | O80: 中 | P80: 財測下修後的市場意見與反應（Zoetis、Trade Desk）。 | R80: 維持 | T80: =IF(R80="維持",J80,IF(R80="排除","無關新聞事件",IFERROR(INDEX(事件規則!$B$2:$B$53,MATCH(S80,事件規則!$A$2:$A$53,0)),""))) -> 財測下修 | U80: =IF(R80="維持",K80,IF(R80="排除",0,IFERROR(INDEX(事件規則!$C$2:$C$53,MATCH(S80,事件規則!$A$2:$A$53,0)),""))) -> 3 | X80: =IF(AND(R80="修改",S80=""),"請選新事件代碼",IF(AND(R80<>"修改",S80<>""),"只有「修改」才需填代碼","")) | AA80: c3d5d0ce78d30af02b6a26cd
A81: 80 | B81: 2026-08-11 | C81: HONA | D81: Honeywell Aerospace Inc. | E81: Jim Cramer Dumps Honeywell Aerospace (HONA) After Shock Guidance Cut Triggers Sharp Selloff | F81: 吉姆·克萊默 (Jim Cramer) 在衝擊指導削減引發急劇拋售後拋售霍尼韋爾航空航天 (HONA) | G81: Yahoo Finance | H81: -0.921 | I81: EARNINGS_WARNING | J81: 財測下修 | K81: 3 | M81: 維持 | O81: 高 | P81: Honeywell Aerospace 意外下修財測，股價大幅下挫。 | R81: 維持 | T81: =IF(R81="維持",J81,IF(R81="排除","無關新聞事件",IFERROR(INDEX(事件規則!$B$2:$B$53,MATCH(S81,事件規則!$A$2:$A$53,0)),""))) -> 財測下修 | U81: =IF(R81="維持",K81,IF(R81="排除",0,IFERROR(INDEX(事件規則!$C$2:$C$53,MATCH(S81,事件規則!$A$2:$A$53,0)),""))) -> 3 | X81: =IF(AND(R81="修改",S81=""),"請選新事件代碼",IF(AND(R81<>"修改",S81<>""),"只有「修改」才需填代碼","")) | AA81: a001c67e640cd10789ab8bc5
A82: 81 | B82: 2026-08-23 | C82: ZTS | D82: Zoetis Inc. Class A Common Stock | E82: Zoetis Stock (ZTS) Opinions on Recent Earnings Guidance Cuts | G82: Quiver Quantitative | H82: -0.011 | I82: EARNINGS_WARNING | J82: 財測下修 | K82: 3 | M82: 維持 | O82: 中 | P82: 財測下修後的市場意見與反應（Zoetis、Trade Desk）。 | R82: 維持 | T82: =IF(R82="維持",J82,IF(R82="排除","無關新聞事件",IFERROR(INDEX(事件規則!$B$2:$B$53,MATCH(S82,事件規則!$A$2:$A$53,0)),""))) -> 財測下修 | U82: =IF(R82="維持",K82,IF(R82="排除",0,IFERROR(INDEX(事件規則!$C$2:$C$53,MATCH(S82,事件規則!$A$2:$A$53,0)),""))) -> 3 | X82: =IF(AND(R82="修改",S82=""),"請選新事件代碼",IF(AND(R82<>"修改",S82<>""),"只有「修改」才需填代碼","")) | AA82: 6dc8608abf13971dd3bbcbb8
A83: 82 | B83: 2026-09-10 | C83: TSN | D83: Tyson Foods, Inc. Common Stock | E83: Tyson Foods at Barclays conference: guidance cut, brands in focus | G83: Investing.com | H83: -0.754 | I83: EARNINGS_WARNING | J83: 財測下修 | K83: 3 | M83: 維持 | O83: 中 | P83: Tyson Foods 在 Barclays 會議談下修財測。 | R83: 維持 | T83: =IF(R83="維持",J83,IF(R83="排除","無關新聞事件",IFERROR(INDEX(事件規則!$B$2:$B$53,MATCH(S83,事件規則!$A$2:$A$53,0)),""))) -> 財測下修 | U83: =IF(R83="維持",K83,IF(R83="排除",0,IFERROR(INDEX(事件規則!$C$2:$C$53,MATCH(S83,事件規則!$A$2:$A$53,0)),""))) -> 3 | X83: =IF(AND(R83="修改",S83=""),"請選新事件代碼",IF(AND(R83<>"修改",S83<>""),"只有「修改」才需填代碼","")) | AA83: b71f865e8b6c82f59ac215c5
A84: 83 | B84: 2026-09-11 | C84: KR | D84: Kroger | E84: Kroger Q2 2026 earnings: stock falls as sales guidance cut | G84: Quartz | H84: -0.961 | I84: EARNINGS_WARNING | J84: 財測下修 | K84: 3 | M84: 維持 | O84: 高 | P84: Kroger 下修銷售財測，股價下跌。 | R84: 維持 | T84: =IF(R84="維持",J84,IF(R84="排除","無關新聞事件",IFERROR(INDEX(事件規則!$B$2:$B$53,MATCH(S84,事件規則!$A$2:$A$53,0)),""))) -> 財測下修 | U84: =IF(R84="維持",K84,IF(R84="排除",0,IFERROR(INDEX(事件規則!$C$2:$C$53,MATCH(S84,事件規則!$A$2:$A$53,0)),""))) -> 3 | X84: =IF(AND(R84="修改",S84=""),"請選新事件代碼",IF(AND(R84<>"修改",S84<>""),"只有「修改」才需填代碼","")) | AA84: fdb2432bfa60eef55321d374
A85: 84 | B85: 2026-09-18 | C85: JBHT | D85: J.B. Hunt | E85: J.B. Hunt's Stock Plunges After Market Misprices Profit Warning | G85: Yahoo Finance | H85: -0.959 | I85: EARNINGS_WARNING | J85: 財測下修 | K85: 3 | M85: 維持 | O85: 高 | P85: J.B. Hunt 發布獲利警告後股價大跌。 | R85: 維持 | T85: =IF(R85="維持",J85,IF(R85="排除","無關新聞事件",IFERROR(INDEX(事件規則!$B$2:$B$53,MATCH(S85,事件規則!$A$2:$A$53,0)),""))) -> 財測下修 | U85: =IF(R85="維持",K85,IF(R85="排除",0,IFERROR(INDEX(事件規則!$C$2:$C$53,MATCH(S85,事件規則!$A$2:$A$53,0)),""))) -> 3 | X85: =IF(AND(R85="修改",S85=""),"請選新事件代碼",IF(AND(R85<>"修改",S85<>""),"只有「修改」才需填代碼","")) | AA85: f74ae452853c7fb50f57225e
A86: 85 | B86: 2026-10-16 | C86: ZTS | D86: Zoetis Inc. Class A Common Stock | E86: Zoetis (ZTS) Hit by Guidance Cuts, Met with Market Shrug | F86: Zoetis (ZTS) 受到指導性下調的打擊，市場對此不以為然 | G86: Yahoo Finance | H86: -0.461 | I86: EARNINGS_WARNING | J86: 財測下修 | K86: 3 | M86: 維持 | O86: 中 | P86: 財測下修後的市場意見與反應（Zoetis、Trade Desk）。 | R86: 維持 | T86: =IF(R86="維持",J86,IF(R86="排除","無關新聞事件",IFERROR(INDEX(事件規則!$B$2:$B$53,MATCH(S86,事件規則!$A$2:$A$53,0)),""))) -> 財測下修 | U86: =IF(R86="維持",K86,IF(R86="排除",0,IFERROR(INDEX(事件規則!$C$2:$C$53,MATCH(S86,事件規則!$A$2:$A$53,0)),""))) -> 3 | X86: =IF(AND(R86="修改",S86=""),"請選新事件代碼",IF(AND(R86<>"修改",S86<>""),"只有「修改」才需填代碼","")) | AA86: 7512ff6d3ceb5edadd9ce246
A87: 86 | B87: 2026-10-24 | C87: META | D87: Meta Platforms | E87: Meta: The Q4 Guide Is The Real Profit Warning (NASDAQ:META) | F87: Meta Platforms 公布第四季指引，警示利潤可能下滑，屬於財務預警事件。 | G87: Seeking Alpha | H87: -0.056 | I87: EARNINGS_WARNING | J87: 財測下修 | K87: 3 | L87: 已分類 | M87: 排除 | O87: 中 | P87: 投資評論文章（作者認為第四季指引是獲利警訊），不是公司公告。 | R87: 排除 | T87: =IF(R87="維持",J87,IF(R87="排除","無關新聞事件",IFERROR(INDEX(事件規則!$B$2:$B$53,MATCH(S87,事件規則!$A$2:$A$53,0)),""))) -> 無關新聞事件 | U87: =IF(R87="維持",K87,IF(R87="排除",0,IFERROR(INDEX(事件規則!$C$2:$C$53,MATCH(S87,事件規則!$A$2:$A$53,0)),""))) -> 0 | X87: =IF(AND(R87="修改",S87=""),"請選新事件代碼",IF(AND(R87<>"修改",S87<>""),"只有「修改」才需填代碼","")) | AA87: e264a84d1b19decda3fc1aa1
A88: 87 | B88: 2026-09-25 | C88: MPC | D88: Marathon Petroleum Corporation Common St | E88: Marathon Petroleum (MPC) Could Be 20% Overvalued Following Diesel Export Ban Review | G88: Yahoo Finance | H88: 0.125 | I88: EXPORT_RESTRICTION | J88: 出口管制 | K88: 3 | M88: 維持 | O88: 中 | P88: 川普支持柴油出口禁令，Marathon Petroleum 面臨政策不確定性。 | R88: 維持 | T88: =IF(R88="維持",J88,IF(R88="排除","無關新聞事件",IFERROR(INDEX(事件規則!$B$2:$B$53,MATCH(S88,事件規則!$A$2:$A$53,0)),""))) -> 出口管制 | U88: =IF(R88="維持",K88,IF(R88="排除",0,IFERROR(INDEX(事件規則!$C$2:$C$53,MATCH(S88,事件規則!$A$2:$A$53,0)),""))) -> 3 | X88: =IF(AND(R88="修改",S88=""),"請選新事件代碼",IF(AND(R88<>"修改",S88<>""),"只有「修改」才需填代碼","")) | AA88: 013747d7355deb6f85ac13a8
A89: 88 | B89: 2026-09-25 | C89: MPC | D89: Marathon Petroleum Corporation Common St | E89: Marathon Petroleum (MPC) Faces Fresh Uncertainty After Trump Backs Diesel Export Ban | G89: Yahoo Finance | H89: -0.923 | I89: EXPORT_RESTRICTION | J89: 出口管制 | K89: 3 | M89: 維持 | O89: 中 | P89: 川普支持柴油出口禁令，Marathon Petroleum 面臨政策不確定性。 | R89: 維持 | T89: =IF(R89="維持",J89,IF(R89="排除","無關新聞事件",IFERROR(INDEX(事件規則!$B$2:$B$53,MATCH(S89,事件規則!$A$2:$A$53,0)),""))) -> 出口管制 | U89: =IF(R89="維持",K89,IF(R89="排除",0,IFERROR(INDEX(事件規則!$C$2:$C$53,MATCH(S89,事件規則!$A$2:$A$53,0)),""))) -> 3 | X89: =IF(AND(R89="修改",S89=""),"請選新事件代碼",IF(AND(R89<>"修改",S89<>""),"只有「修改」才需填代碼","")) | AA89: 7af0ec7ca161a30427a2941f
A90: 89 | B90: 2026-09-28 | C90: GS | D90: Goldman Sachs | E90: How a U.S. diesel export ban would play out, according to Goldman Sachs | G90: MarketWatch | H90: -0.124 | I90: EXPORT_RESTRICTION | J90: 出口管制 | K90: 3 | M90: 排除 | O90: 高 | P90: 高盛對柴油出口禁令的分析，高盛不是受影響公司。 | R90: 排除 | T90: =IF(R90="維持",J90,IF(R90="排除","無關新聞事件",IFERROR(INDEX(事件規則!$B$2:$B$53,MATCH(S90,事件規則!$A$2:$A$53,0)),""))) -> 無關新聞事件 | U90: =IF(R90="維持",K90,IF(R90="排除",0,IFERROR(INDEX(事件規則!$C$2:$C$53,MATCH(S90,事件規則!$A$2:$A$53,0)),""))) -> 0 | X90: =IF(AND(R90="修改",S90=""),"請選新事件代碼",IF(AND(R90<>"修改",S90<>""),"只有「修改」才需填代碼","")) | AA90: d431b18069310d29cc900ab8
A91: 90 | B91: 2026-09-29 | C91: XOM | D91: ExxonMobil | E91: ExxonMobil Got a $180 Target as Trump Weighed a Diesel Export Ban. Here’s What It Means for the Stock | G91: TIKR.com | H91: 0.053 | I91: EXPORT_RESTRICTION | J91: 出口管制 | K91: 3 | M91: 排除 | O91: 中 | P91: Exxon 目標價評論，柴油出口禁令只是背景。 | R91: 排除 | T91: =IF(R91="維持",J91,IF(R91="排除","無關新聞事件",IFERROR(INDEX(事件規則!$B$2:$B$53,MATCH(S91,事件規則!$A$2:$A$53,0)),""))) -> 無關新聞事件 | U91: =IF(R91="維持",K91,IF(R91="排除",0,IFERROR(INDEX(事件規則!$C$2:$C$53,MATCH(S91,事件規則!$A$2:$A$53,0)),""))) -> 0 | X91: =IF(AND(R91="修改",S91=""),"請選新事件代碼",IF(AND(R91<>"修改",S91<>""),"只有「修改」才需填代碼","")) | AA91: 7c39112bfd50c2aee6447560
A92: 91 | B92: 2026-10-06 | C92: MPC | D92: Marathon Petroleum Corporation Common St | E92: Marathon Petroleum (MPC) Stock May Be 26% Undervalued After Diesel Export Ban Risk | G92: Simply Wall Street | H92: -0.199 | I92: EXPORT_RESTRICTION | J92: 出口管制 | K92: 3 | M92: 維持 | O92: 中 | P92: 川普支持柴油出口禁令，Marathon Petroleum 面臨政策不確定性。 | R92: 維持 | T92: =IF(R92="維持",J92,IF(R92="排除","無關新聞事件",IFERROR(INDEX(事件規則!$B$2:$B$53,MATCH(S92,事件規則!$A$2:$A$53,0)),""))) -> 出口管制 | U92: =IF(R92="維持",K92,IF(R92="排除",0,IFERROR(INDEX(事件規則!$C$2:$C$53,MATCH(S92,事件規則!$A$2:$A$53,0)),""))) -> 3 | X92: =IF(AND(R92="修改",S92=""),"請選新事件代碼",IF(AND(R92<>"修改",S92<>""),"只有「修改」才需填代碼","")) | AA92: 9b4f93e7a6837315fc805449
A93: 92 | B93: 2026-08-10 | C93: MSFT | D93: Microsoft Corporation | E93: Microsoft Stock Facing Margin Pressures | F93: 微軟股票面臨獲利壓力 | G93: Forbes | H93: -0.951 | I93: OPERATING_DETERIORATION | J93: 營運惡化 | K93: 3 | M93: 排除 | O93: 中 | P93: 投資分析或一般財報解讀，提到毛利壓力但不是新的營運惡化事件。 | R93: 排除 | T93: =IF(R93="維持",J93,IF(R93="排除","無關新聞事件",IFERROR(INDEX(事件規則!$B$2:$B$53,MATCH(S93,事件規則!$A$2:$A$53,0)),""))) -> 無關新聞事件 | U93: =IF(R93="維持",K93,IF(R93="排除",0,IFERROR(INDEX(事件規則!$C$2:$C$53,MATCH(S93,事件規則!$A$2:$A$53,0)),""))) -> 0 | X93: =IF(AND(R93="修改",S93=""),"請選新事件代碼",IF(AND(R93<>"修改",S93<>""),"只有「修改」才需填代碼","")) | AA93: d5cdd82b8f37fa119d28d666
A94: 93 | B94: 2026-08-11 | C94: FISV | D94: Fiserv, Inc. | E94: Fiserv Cuts 2026 Outlook as Margin Pressure Tests Its Recovery Story | F94: Fiserv 下調 2026 年展望，因利潤率壓力考驗其復甦故事 | G94: The Globe and Mail | H94: -0.954 | I94: OPERATING_DETERIORATION | J94: 營運惡化 | K94: 3 | M94: 修改 | N94: EARNINGS_WARNING | O94: 高 | P94: Fiserv 下修 2026 年展望，屬財測下修（毛利壓力為原因）。 | R94: 修改 | S94: EARNINGS_WARNING | T94: =IF(R94="維持",J94,IF(R94="排除","無關新聞事件",IFERROR(INDEX(事件規則!$B$2:$B$53,MATCH(S94,事件規則!$A$2:$A$53,0)),""))) -> 財測下修 | U94: =IF(R94="維持",K94,IF(R94="排除",0,IFERROR(INDEX(事件規則!$C$2:$C$53,MATCH(S94,事件規則!$A$2:$A$53,0)),""))) -> 3 | X94: =IF(AND(R94="修改",S94=""),"請選新事件代碼",IF(AND(R94<>"修改",S94<>""),"只有「修改」才需填代碼","")) | AA94: 4948464033b1b83979851eed
A95: 94 | B95: 2026-08-15 | C95: KR | D95: Kroger | E95: Kroger raises dividend 11.4% and announces $2B buyback amid Q1 sales slowdown and margin pressure. | F95: 由於第一季銷售放緩和利潤率壓力，克羅格將股息提高 11.4% 並宣布 20 億美元回購。 | G95: Pluang | H95: -0.875 | I95: OPERATING_DETERIORATION | J95: 營運惡化 | K95: 3 | M95: 排除 | O95: 中 | P95: 投資分析或一般財報解讀，提到毛利壓力但不是新的營運惡化事件。 | R95: 排除 | T95: =IF(R95="維持",J95,IF(R95="排除","無關新聞事件",IFERROR(INDEX(事件規則!$B$2:$B$53,MATCH(S95,事件規則!$A$2:$A$53,0)),""))) -> 無關新聞事件 | U95: =IF(R95="維持",K95,IF(R95="排除",0,IFERROR(INDEX(事件規則!$C$2:$C$53,MATCH(S95,事件規則!$A$2:$A$53,0)),""))) -> 0 | X95: =IF(AND(R95="修改",S95=""),"請選新事件代碼",IF(AND(R95<>"修改",S95<>""),"只有「修改」才需填代碼","")) | AA95: 8731eb2aa8972fd6e8faf4d7
A96: 95 | B96: 2026-08-16 | C96: COIN | D96: Coinbase | E96: Bitcoin demand weakens as Coinbase premium inde... | F96: 隨著 Coinbase 溢價指數下降，比特幣需求減弱 | G96: Pluang | H96: -0.947 | I96: OPERATING_DETERIORATION | J96: 營運惡化 | K96: 3 | M96: 排除 | O96: 高 | P96: 比特幣需求與 Coinbase 溢價指標，不是 Coinbase 營運惡化。 | R96: 排除 | T96: =IF(R96="維持",J96,IF(R96="排除","無關新聞事件",IFERROR(INDEX(事件規則!$B$2:$B$53,MATCH(S96,事件規則!$A$2:$A$53,0)),""))) -> 無關新聞事件 | U96: =IF(R96="維持",K96,IF(R96="排除",0,IFERROR(INDEX(事件規則!$C$2:$C$53,MATCH(S96,事件規則!$A$2:$A$53,0)),""))) -> 0 | X96: =IF(AND(R96="修改",S96=""),"請選新事件代碼",IF(AND(R96<>"修改",S96<>""),"只有「修改」才需填代碼","")) | AA96: 8223eec336e2ca59113293fd
A97: 96 | B97: 2026-08-20 | C97: FISV | D97: Fiserv, Inc. | E97: Fiserv's 2026 Outlook Cut Puts Revenue and Margin Pressure in Focus | G97: finance.yahoo.com | H97: -0.95 | I97: OPERATING_DETERIORATION | J97: 營運惡化 | K97: 3 | M97: 修改 | N97: EARNINGS_WARNING | O97: 高 | P97: Fiserv 下修 2026 年展望，屬財測下修（毛利壓力為原因）。 | R97: 修改 | S97: EARNINGS_WARNING | T97: =IF(R97="維持",J97,IF(R97="排除","無關新聞事件",IFERROR(INDEX(事件規則!$B$2:$B$53,MATCH(S97,事件規則!$A$2:$A$53,0)),""))) -> 財測下修 | U97: =IF(R97="維持",K97,IF(R97="排除",0,IFERROR(INDEX(事件規則!$C$2:$C$53,MATCH(S97,事件規則!$A$2:$A$53,0)),""))) -> 3 | X97: =IF(AND(R97="修改",S97=""),"請選新事件代碼",IF(AND(R97<>"修改",S97<>""),"只有「修改」才需填代碼","")) | AA97: b85fb47a39549e96690d81d4
A98: 97 | B98: 2026-08-20 | C98: BG | D98: Bunge Global | E98: How Revenue Growth Amid Margin Pressure Will Impact Bunge Global (BG) Investors | G98: simplywall.st | H98: -0.239 | I98: OPERATING_DETERIORATION | J98: 營運惡化 | K98: 3 | M98: 排除 | O98: 中 | P98: 投資分析或一般財報解讀，提到毛利壓力但不是新的營運惡化事件。 | R98: 排除 | T98: =IF(R98="維持",J98,IF(R98="排除","無關新聞事件",IFERROR(INDEX(事件規則!$B$2:$B$53,MATCH(S98,事件規則!$A$2:$A$53,0)),""))) -> 無關新聞事件 | U98: =IF(R98="維持",K98,IF(R98="排除",0,IFERROR(INDEX(事件規則!$C$2:$C$53,MATCH(S98,事件規則!$A$2:$A$53,0)),""))) -> 0 | X98: =IF(AND(R98="修改",S98=""),"請選新事件代碼",IF(AND(R98<>"修改",S98<>""),"只有「修改」才需填代碼","")) | AA98: ee61869adc7dc1e65e326d0e
A99: 98 | B99: 2026-08-21 | C99: CLX | D99: Clorox | E99: Is Clorox Stock Worth Buying as GOJO Growth Meets Margin Pressure? | G99: Yahoo Finance | H99: 0.213 | I99: OPERATING_DETERIORATION | J99: 營運惡化 | K99: 3 | M99: 排除 | O99: 中 | P99: 投資分析或一般財報解讀，提到毛利壓力但不是新的營運惡化事件。 | R99: 排除 | T99: =IF(R99="維持",J99,IF(R99="排除","無關新聞事件",IFERROR(INDEX(事件規則!$B$2:$B$53,MATCH(S99,事件規則!$A$2:$A$53,0)),""))) -> 無關新聞事件 | U99: =IF(R99="維持",K99,IF(R99="排除",0,IFERROR(INDEX(事件規則!$C$2:$C$53,MATCH(S99,事件規則!$A$2:$A$53,0)),""))) -> 0 | X99: =IF(AND(R99="修改",S99=""),"請選新事件代碼",IF(AND(R99<>"修改",S99<>""),"只有「修改」才需填代碼","")) | AA99: b3bfb07265a165d7e7332a07
A100: 99 | B100: 2026-08-26 | C100: EME | D100: Emcor | E100: Can EMCOR's Mechanical Construction Growth Offset Margin Pressure? | G100: Yahoo Finance | H100: 0.847 | I100: OPERATING_DETERIORATION | J100: 營運惡化 | K100: 3 | M100: 排除 | O100: 中 | P100: 投資分析或一般財報解讀，提到毛利壓力但不是新的營運惡化事件。 | R100: 排除 | T100: =IF(R100="維持",J100,IF(R100="排除","無關新聞事件",IFERROR(INDEX(事件規則!$B$2:$B$53,MATCH(S100,事件規則!$A$2:$A$53,0)),""))) -> 無關新聞事件 | U100: =IF(R100="維持",K100,IF(R100="排除",0,IFERROR(INDEX(事件規則!$C$2:$C$53,MATCH(S100,事件規則!$A$2:$A$53,0)),""))) -> 0 | X100: =IF(AND(R100="修改",S100=""),"請選新事件代碼",IF(AND(R100<>"修改",S100<>""),"只有「修改」才需填代碼","")) | AA100: 5d78fbb6f4e63672fc45fc0c
A101: 100 | B101: 2026-08-28 | C101: HRL | D101: Hormel Foods Corporation Common Stock | E101: HRL Q2 Deep Dive: Volumes Decline, Margin Pressures Persist, Management Eyes Brand Investment | G101: Yahoo Finance | H101: -0.948 | I101: OPERATING_DETERIORATION | J101: 營運惡化 | K101: 3 | M101: 維持 | O101: 中 | P101: Hormel 銷量下滑、毛利壓力持續。 | R101: 維持 | T101: =IF(R101="維持",J101,IF(R101="排除","無關新聞事件",IFERROR(INDEX(事件規則!$B$2:$B$53,MATCH(S101,事件規則!$A$2:$A$53,0)),""))) -> 營運惡化 | U101: =IF(R101="維持",K101,IF(R101="排除",0,IFERROR(INDEX(事件規則!$C$2:$C$53,MATCH(S101,事件規則!$A$2:$A$53,0)),""))) -> 3 | X101: =IF(AND(R101="修改",S101=""),"請選新事件代碼",IF(AND(R101<>"修改",S101<>""),"只有「修改」才需填代碼","")) | AA101: d83699b13932c7eb7a3bb9a5
A102: 101 | B102: 2026-08-28 | C102: HPQ | D102: HP Inc. Common Stock | E102: HPQ Q2 Deep Dive: AI PCs Drive Growth Amid Margin Pressures and Cautious Outlook | G102: Yahoo Finance | H102: 0.149 | I102: OPERATING_DETERIORATION | J102: 營運惡化 | K102: 3 | M102: 排除 | O102: 中 | P102: 投資分析或一般財報解讀，提到毛利壓力但不是新的營運惡化事件。 | R102: 排除 | T102: =IF(R102="維持",J102,IF(R102="排除","無關新聞事件",IFERROR(INDEX(事件規則!$B$2:$B$53,MATCH(S102,事件規則!$A$2:$A$53,0)),""))) -> 無關新聞事件 | U102: =IF(R102="維持",K102,IF(R102="排除",0,IFERROR(INDEX(事件規則!$C$2:$C$53,MATCH(S102,事件規則!$A$2:$A$53,0)),""))) -> 0 | X102: =IF(AND(R102="修改",S102=""),"請選新事件代碼",IF(AND(R102<>"修改",S102<>""),"只有「修改」才需填代碼","")) | AA102: a44ba651f906be9b1d3a4bc9
A103: 102 | B103: 2026-09-01 | C103: CLX | D103: Clorox | E103: Clorox Slides as Weak Demand, Margin Pressure, and Cautious FY27 Outlook Remain in Focus | G103: Quiver Quantitative | H103: -0.962 | I103: OPERATING_DETERIORATION | J103: 營運惡化 | K103: 3 | M103: 維持 | O103: 中 | P103: Clorox 需求疲弱、毛利壓力，FY27 展望保守，股價下滑。 | R103: 維持 | T103: =IF(R103="維持",J103,IF(R103="排除","無關新聞事件",IFERROR(INDEX(事件規則!$B$2:$B$53,MATCH(S103,事件規則!$A$2:$A$53,0)),""))) -> 營運惡化 | U103: =IF(R103="維持",K103,IF(R103="排除",0,IFERROR(INDEX(事件規則!$C$2:$C$53,MATCH(S103,事件規則!$A$2:$A$53,0)),""))) -> 3 | X103: =IF(AND(R103="修改",S103=""),"請選新事件代碼",IF(AND(R103<>"修改",S103<>""),"只有「修改」才需填代碼","")) | AA103: 9cebe0a71c84871dc5c89d97
A104: 103 | B104: 2026-09-11 | C104: TSLA | D104: Tesla, Inc. | E104: China’s Battery EV Market Grows as Tesla (TSLA Stock) Posts Third Straight Monthly Sales Decline | G104: CarbonCredits.com | H104: 0.931 | I104: OPERATING_DETERIORATION | J104: 營運惡化 | K104: 3 | M104: 維持 | O104: 中 | P104: Tesla 在中國連續第三個月銷量下滑。 | R104: 維持 | T104: =IF(R104="維持",J104,IF(R104="排除","無關新聞事件",IFERROR(INDEX(事件規則!$B$2:$B$53,MATCH(S104,事件規則!$A$2:$A$53,0)),""))) -> 營運惡化 | U104: =IF(R104="維持",K104,IF(R104="排除",0,IFERROR(INDEX(事件規則!$C$2:$C$53,MATCH(S104,事件規則!$A$2:$A$53,0)),""))) -> 3 | X104: =IF(AND(R104="修改",S104=""),"請選新事件代碼",IF(AND(R104<>"修改",S104<>""),"只有「修改」才需填代碼","")) | AA104: e93659c09f89627db22cf26f
A105: 104 | B105: 2026-09-11 | C105: CLX | D105: Clorox | E105: Clorox Falls as Investors Weigh Margin Pressure and a Cautious FY27 Setup | G105: Quiver Quantitative | H105: -0.947 | I105: OPERATING_DETERIORATION | J105: 營運惡化 | K105: 3 | M105: 維持 | O105: 中 | P105: Clorox 需求疲弱、毛利壓力，FY27 展望保守，股價下滑。 | R105: 維持 | T105: =IF(R105="維持",J105,IF(R105="排除","無關新聞事件",IFERROR(INDEX(事件規則!$B$2:$B$53,MATCH(S105,事件規則!$A$2:$A$53,0)),""))) -> 營運惡化 | U105: =IF(R105="維持",K105,IF(R105="排除",0,IFERROR(INDEX(事件規則!$C$2:$C$53,MATCH(S105,事件規則!$A$2:$A$53,0)),""))) -> 3 | X105: =IF(AND(R105="修改",S105=""),"請選新事件代碼",IF(AND(R105<>"修改",S105<>""),"只有「修改」才需填代碼","")) | AA105: 8b9128532f72eb788dcb809d
A106: 105 | B106: 2026-09-15 | C106: CPRT | D106: Copart, Inc. | E106: How Copart’s (CPRT) Slower EPS and Margin Compression Has Changed Its Investment Story | G106: Yahoo Finance | H106: 0.127 | I106: OPERATING_DETERIORATION | J106: 營運惡化 | K106: 3 | M106: 排除 | O106: 中 | P106: 投資分析或一般財報解讀，提到毛利壓力但不是新的營運惡化事件。 | R106: 排除 | T106: =IF(R106="維持",J106,IF(R106="排除","無關新聞事件",IFERROR(INDEX(事件規則!$B$2:$B$53,MATCH(S106,事件規則!$A$2:$A$53,0)),""))) -> 無關新聞事件 | U106: =IF(R106="維持",K106,IF(R106="排除",0,IFERROR(INDEX(事件規則!$C$2:$C$53,MATCH(S106,事件規則!$A$2:$A$53,0)),""))) -> 0 | X106: =IF(AND(R106="修改",S106=""),"請選新事件代碼",IF(AND(R106<>"修改",S106<>""),"只有「修改」才需填代碼","")) | AA106: 57964828f90fa7454fc5fa7b
A107: 106 | B107: 2026-09-16 | C107: LEN | D107: Lennar Corporation Class A Common Stock | E107: Lennar Fiscal Q3 Adjusted Earnings, Revenue Decline | G107: Yahoo Finance | H107: -0.908 | I107: OPERATING_DETERIORATION | J107: 營運惡化 | K107: 3 | M107: 維持 | O107: 中 | P107: Lennar 第三財季調整後獲利與營收下滑。 | R107: 維持 | T107: =IF(R107="維持",J107,IF(R107="排除","無關新聞事件",IFERROR(INDEX(事件規則!$B$2:$B$53,MATCH(S107,事件規則!$A$2:$A$53,0)),""))) -> 營運惡化 | U107: =IF(R107="維持",K107,IF(R107="排除",0,IFERROR(INDEX(事件規則!$C$2:$C$53,MATCH(S107,事件規則!$A$2:$A$53,0)),""))) -> 3 | X107: =IF(AND(R107="修改",S107=""),"請選新事件代碼",IF(AND(R107<>"修改",S107<>""),"只有「修改」才需填代碼","")) | AA107: ff424b0a675f590eef5dfdb7
...

Sheet 事件規則
A1: Event_Code | B1: 事件中文 | C1: Level
A2: ACCOUNTING_FRAUD | B2: 會計舞弊 | C2: 5
A3: BANKRUPTCY | B3: 破產 | C3: 5
A4: DEFAULT | B4: 違約 | C4: 5
A5: DELISTING | B5: 下市 | C5: 5
A6: GOING_CONCERN | B6: 繼續經營疑慮 | C6: 5
A7: LIQUIDITY_CRISIS | B7: 流動性危機 | C7: 5
A8: TRADING_SUSPENSION | B8: 停牌 | C8: 5
A9: ANTITRUST_INVESTIGATION | B9: 反壟斷調查 | C9: 4
A10: AUDITOR_RESIGNATION | B10: 會計師辭任 | C10: 4
A11: CREDIT_DOWNGRADE | B11: 信用調降 | C11: 4
A12: ENVIRONMENTAL_INCIDENT | B12: 重大環境事故 | C12: 4
A13: EXECUTIVE_MISCONDUCT | B13: 高管不當行為 | C13: 4
... A53: UNKNOWN | B53: 待人工覆核 | C53: 0
A55: 來源：negative-news 的 Parameter_Event.xlsx（Event 工作表），2026-10-26 讀取。
